Workbook

Sheet Dashboard
B2: SIX SIGMA / SSBB PROJECT TRACKING — DASHBOARD
B3: Live summary of all improvement projects | Source sheet: 'Project Tracking' | Data rows 6-85
B5: TOTAL PROJECTS | D5: ACHIEVED | F5: ON TRACK | H5: NEEDS ATTENTION | J5: NO DATA | L5: ACHIEVEMENT RATE
B6: =COUNT('Project Tracking'!$A$6:$A$84) -> 78 | D6: =COUNTIF('Project Tracking'!$X$6:$X$84,"Achieved") -> 16 | F6: =COUNTIF('Project Tracking'!$X$6:$X$84,"On Track") -> 9 | H6: =COUNTIF('Project Tracking'!$X$6:$X$84,"Needs Attention") -> 31 | J6: =COUNTIF('Project Tracking'!$X$6:$X$84,"No Data") -> 22 | L6: =IFERROR(COUNTIF('Project Tracking'!$X$6:$X$84,"Achieved")/COUNT('Project Tracking'!$A$6:$A$84),0) -> 0.20512821
B10: STATUS BREAKDOWN | E10: PROJECTS BY BATCH | H10: PROJECTS BY LOCATION / UNIT
B11: Status | C11: Count | E11: Batch | F11: Count | H11: Location | I11: Count
B12: Achieved | C12: =COUNTIF('Project Tracking'!$X$6:$X$84,"Achieved") -> 16 | E12: Batch I | F12: =COUNTIF('Project Tracking'!$B$6:$B$84,"I") -> 33 | H12: Unit-I | I12: =SUMPRODUCT(--(TRIM('Project Tracking'!$E$6:$E$84)=H12)) -> 3
B13: On Track | C13: =COUNTIF('Project Tracking'!$X$6:$X$84,"On Track") -> 9 | E13: Batch II | F13: =COUNTIF('Project Tracking'!$B$6:$B$84,"II") -> 46 | H13: Unit-III | I13: =SUMPRODUCT(--(TRIM('Project Tracking'!$E$6:$E$84)=H13)) -> 42
B14: Needs Attention | C14: =COUNTIF('Project Tracking'!$X$6:$X$84,"Needs Attention") -> 31 | H14: Unit-IV | I14: =SUMPRODUCT(--(TRIM('Project Tracking'!$E$6:$E$84)=H14)) -> 26
B15: No Data | C15: =COUNTIF('Project Tracking'!$X$6:$X$84,"No Data") -> 22 | H15: HO | I15: =SUMPRODUCT(--(TRIM('Project Tracking'!$E$6:$E$84)=H15)) -> 5
H16: JSBIL | I16: =SUMPRODUCT(--(TRIM('Project Tracking'!$E$6:$E$84)=H16)) -> 1
B17: TOP DEPARTMENTS BY PROJECT COUNT | H17: Mackeil | I17: =SUMPRODUCT(--(TRIM('Project Tracking'!$E$6:$E$84)=H17)) -> 2
B18: Department | C18: Count | E18: PERFORMANCE METRICS
B19: Business Excellence | C19: =SUMPRODUCT(--(TRIM('Project Tracking'!$F$6:$F$84)=B19)) -> 4 | E19: Avg. Progress % (all projects) | F19: =IFERROR(AVERAGE('Project Tracking'!$W$6:$W$84),0) -> 0.37997077
B20: MBF Operation | C20: =SUMPRODUCT(--(TRIM('Project Tracking'!$F$6:$F$84)=B20)) -> 5 | E20: Median Progress % (all projects) | F20: =IFERROR(MEDIAN('Project Tracking'!$W$6:$W$84),0) -> 0.31987988
B21: Human Resource | C21: =SUMPRODUCT(--(TRIM('Project Tracking'!$F$6:$F$84)=B21)) -> 5 | E21: Projects w/ Increasing target | F21: =COUNTIF('Project Tracking'!$H$6:$H$84,"Increasing") -> 38
B22: Ferro Operations | C22: =SUMPRODUCT(--(TRIM('Project Tracking'!$F$6:$F$84)=B22)) -> 4 | E22: Projects w/ Decreasing target | F22: =SUMPRODUCT((LEFT('Project Tracking'!$H$6:$H$84,4)="Decr")*1) -> 38
B23: Operation | C23: =SUMPRODUCT(--(TRIM('Project Tracking'!$F$6:$F$84)=B23)) -> 4 | E23: Projects reporting data (non-blank) | F23: =COUNT('Project Tracking'!$W$6:$W$84) -> 56
B24: DIP Mechanical | C24: =SUMPRODUCT(--(TRIM('Project Tracking'!$F$6:$F$84)=B24)) -> 4 | E24: Distinct Locations / Units | F24: 6
B25: DRI | C25: =SUMPRODUCT(--(TRIM('Project Tracking'!$F$6:$F$84)=B25)) -> 4 | E25: Distinct Departments | F25: 42
B26: CPP Operations | C26: =SUMPRODUCT(--(TRIM('Project Tracking'!$F$6:$F$84)=B26)) -> 3
B27: DIP Marketing | C27: =SUMPRODUCT(--(TRIM('Project Tracking'!$F$6:$F$84)=B27)) -> 3
B28: Central Electrical | C28: =SUMPRODUCT(--(TRIM('Project Tracking'!$F$6:$F$84)=B28)) -> 2
B29: DIP Operation | C29: =SUMPRODUCT(--(TRIM('Project Tracking'!$F$6:$F$84)=B29)) -> 1
B30: RMHS Electrical | C30: =SUMPRODUCT(--(TRIM('Project Tracking'!$F$6:$F$84)=B30)) -> 2
B32: VISUAL ANALYSIS
B73: Note: All figures are formulas linked live to the 'Project Tracking' sheet (rows 6-85) and refresh automatically when that data changes. 'Achievement Rate' = Achieved projects ÷ Total projects.

Sheet Project Tracking
A1: SIX SIGMA / SSBB PROJECT TRACKING SHEET
A2: Participants | Project Theme | Baseline Period, UOM & Data | Target | Monthly Tracking (Jan–Sep) | Location & Department
A4: PROJECT & PARTICIPANT INFO | H4: PROJECT TYPE | K4: BASELINE & TARGET | M4: MONTH-WISE ACTUAL TRACKING (JAN – JUN) | V4: PERFORMANCE SUMMARY
A5: S.No | B5: Batch | C5: Employee Code | D5: Participant's Name | E5: Location / Unit | G5: Project Theme / Title | H5: Improvement Direction | I5: Baseline UOM | J5: Baseline Period | K5: Baseline Data | L5: Target | M5: Jan-26 | N5: Feb-26 | O5: Mar-26 | P5: Apr-26 | Q5: May-26 | R5: Jun-26 | S5: 46204 | T5: 46235 | U5: 46266 | V5: Average (Actual) | W5: Progress % | X5: Status | Y5: Project File | Z5: Review date | AA5: Comment | AB5: Target Date
A6: 57 | B6: II | C6: 2762 | D6: Abdur Rowf | E6: Unit-III | F6: Store | G6: Reducing Non moving items of Central store values from 6.3Cr. to <3.15Cr. INR | H6: Decreasing | I6: Cr | K6: 6.3 | L6: 3.15 | V6: =IFERROR(AVERAGE(M6:S6),"") | W6: =IFERROR(IF(V6="","",IF(H6="Increasing",(V6-K6)/(L6-K6),(K6-V6)/(K6-L6))),"") | X6: =IF(W6="","No Data",IF(W6>=1,"Achieved",IF(W6>=0.5,"On Track","Needs Attention"))) -> No Data | Y6: SSBB Project-Abdur Rowf | Z6: 46244 | AA6: 1. issue hopper 2.Monsoon wise data for six month 3.inser comment | AB6: =IF(V6>K6,"U6/K6*100","0") -> U6/K6*100
A7: 1 | B7: I | C7: 16923 | D7: Akram Imran | E7: Unit-I | F7: Operations | G7: Improve the Avg Productivity of Kiln per Month from 41.18 ton to 45 ton for Kiln#1 | H7: Increasing | I7: TPD | J7: Dec'24 -Sept'25 | K7: 41.18 | L7: 45 | M7: 28.76 | N7: 42.01 | O7: 30.72 | P7: 42.75 | Q7: 39.423077 | R7: 42.666667 | S7: 41.701923 | V7: =IFERROR(AVERAGE(M7:S7),"") -> 38.290238 | W7: =IFERROR(IF(V7="","",IF(H7="Increasing",(V7-K7)/(L7-K7),(K7-V7)/(K7-L7))),"") -> -0.75648217 | X7: =IF(W7="","No Data",IF(W7>=1,"Achieved",IF(W7>=0.5,"On Track","Needs Attention"))) -> Needs Attention | Y7: SSBB Project-Akram Imran | Z7: 46244 | AA7: 1.Issue hopper 2. Insert comment | AB7: =IF(V7>K7,"U6/K6","0") -> 0
A8: 13 | B8: II | C8: 5503 | D8: Alok Mandal | E8: Unit-III | F8: Operation | G8: Reduce the average Gox Venting Loss per month from 339 to 180 MT. | H8: Decreasing | V8: =IFERROR(AVERAGE(M8:S8),"") | W8: =IFERROR(IF(V8="","",IF(H8="Increasing",(V8-K8)/(L8-K8),(K8-V8)/(K8-L8))),"") | X8: =IF(W8="","No Data",IF(W8>=1,"Achieved",IF(W8>=0.5,"On Track","Needs Attention"))) -> No Data | Y8: SSBB Project-Alok Mandal | Z8: 46244 | AA8: 1.Issue hopper 2. Insert comment | AB8: =IF(V8>K8,"U6/K6*100","0") -> 0
A9: 50 | B9: II | C9: 2954 | D9: Amit Dahari | E9: Unit-III | F9: MBF Electrical | G9: Reduce the Avg Specific energy consumption of MBF per month from 134.4 kWH/THM to 125 KWH/THM. | H9: Decreasing | I9: KWH/THM | K9: 134.4 | L9: 125 | V9: =IFERROR(AVERAGE(M9:S9),"") | W9: =IFERROR(IF(V9="","",IF(H9="Increasing",(V9-K9)/(L9-K9),(K9-V9)/(K9-L9))),"") | X9: =IF(W9="","No Data",IF(W9>=1,"Achieved",IF(W9>=0.5,"On Track","Needs Attention"))) -> No Data | Y9: SSBB Project-Amit Dahari | Z9: 46244 | AA9: 1.Issue hopper 2. Insert comment | AB9: =IF(V9>K9,"U6/K6*100","0") -> U6/K6*100
A10: 69 | B10: I | C10: 10223 | D10: Amitava Dasgupta | E10: HO | F10: DIP Marketing | G10: Re-establish the tender data base (tender missing) ------- reducing tender processing time from ----- to ----- without adverse implication. | I10: Nos | V10: =IFERROR(AVERAGE(M10:S10),"") | W10: =IFERROR(IF(V10="","",IF(H10="Increasing",(V10-K10)/(L10-K10),(K10-V10)/(K10-L10))),"") | X10: =IF(W10="","No Data",IF(W10>=1,"Achieved",IF(W10>=0.5,"On Track","Needs Attention"))) -> No Data | Y10: SSBB Project-Amitava Dasgupta | Z10: 46244 | AA10: 1.Issue hopper 2. Insert comment | AB10: =IF(V10>K10,"U6/K6*100","0") -> 0
A11: 73 | B11: I | C11: 10642 | D11: Amitava Mukherjee | E11: HO | F11: Human Resource | G11: Improve the Manpower engagement of HO from -- % per month to --- % per month. | H11: Increasing | I11: 0 | V11: =IFERROR(AVERAGE(M11:S11),"") | W11: =IFERROR(IF(V11="","",IF(H11="Increasing",(V11-K11)/(L11-K11),(K11-V11)/(K11-L11))),"") | X11: =IF(W11="","No Data",IF(W11>=1,"Achieved",IF(W11>=0.5,"On Track","Needs Attention"))) -> No Data | Y11: SSBB Project-Amitava Mukherjee | Z11: 46244 | AA11: 1.Issue hopper 2. Insert comment
A12: 59 | B12: I | C12: 47015 | D12: Aniruddha Ray | E12: Unit-IV | F12: Accounts and Finance | G12: Reduce the Invoice processing time of unit IV from --- to -----. | H12: Decreasing | I12: 0 | V12: =IFERROR(AVERAGE(M12:S12),"") | W12: =IFERROR(IF(V12="","",IF(H12="Increasing",(V12-K12)/(L12-K12),(K12-V12)/(K12-L12))),"") | X12: =IF(W12="","No Data",IF(W12>=1,"Achieved",IF(W12>=0.5,"On Track","Needs Attention"))) -> No Data | Y12: SSBB Project-Aniruddha Ray | Z12: 46244 | AA12: 1.Issue hopper 2. Insert comment 3. Aug-26 ( Plan)
A13: 52 | B13: I | C13: 4781 | D13: Anupam Basak | E13: Unit-III | F13: Quality | G13: To reduce the Avg Variation of Basicity of Sinter Plant 1 from 0.107 to 0.06 . | H13: Decreasing | I13: 0 | J13: Aug'25-Dec'25 | K13: 0.107 | L13: 0.06 | M13: 0.099 | N13: 0.106 | O13: 0.105 | P13: 0.106 | Q13: 0.102 | R13: 0.097 | V13: =IFERROR(AVERAGE(M13:S13),"") -> 0.1025 | W13: =IFERROR(IF(V13="","",IF(H13="Increasing",(V13-K13)/(L13-K13),(K13-V13)/(K13-L13))),"") -> 0.095744681 | X13: =IF(W13="","No Data",IF(W13>=1,"Achieved",IF(W13>=0.5,"On Track","Needs Attention"))) -> Needs Attention | Y13: SSBB Project-Anupam Basak | Z13: 46246 | AA13: 1.Target to be check 2. insert comment 3. Legacy coal to constrained to used and showing the trends 4. Last two years of Raining season data to be compare | AB13: 46260
A14: 36 | B14: II | C14: 0 | D14: Arijit Mondal | E14: Unit-IV | F14: CPP Operations | G14: Increase the Steam Generation rate of 85 TPH Boiler per month from 31048 to 548972 ton/Month | H14: Increasing | I14: Ton/Month | J14: Jan-25-Nov-25 | K14: 31048 | L14: 48972 | M14: 26349 | N14: 38713 | O14: 51859 | P14: 37485 | Q14: 40115 | R14: 36362 | S14: 41116 | V14: =IFERROR(AVERAGE(M14:S14),"") -> 38857 | W14: =IFERROR(IF(V14="","",IF(H14="Increasing",(V14-K14)/(L14-K14),(K14-V14)/(K14-L14))),"") -> 0.43567284 | X14: =IF(W14="","No Data",IF(W14>=1,"Achieved",IF(W14>=0.5,"On Track","Needs Attention"))) -> Needs Attention | Y14: SSBB Project-Arijit Mondal | Z14: 46246 | AA14: 1. Required work will be completed in Up-coming capital shutdown. | AB14: 46305
A15: 37 | B15: I | C15: 45143 | D15: Arun Thatoi | E15: Unit-IV | F15: Central Electrical | G15: Increase Average Load Factor of Unit-IV from 72.49 % to >80 % per Day | H15: Increasing | I15: % | J15: Aug'25-Dec'25 | K15: 72.49 | L15: 80 | M15: 71.28 | N15: 74.85 | O15: 74.86 | P15: 78.85 | Q15: 73.82 | R15: 70.31 | S15: 69.4 | V15: =IFERROR(AVERAGE(M15:S15),"") -> 73.338571 | W15: =IFERROR(IF(V15="","",IF(H15="Increasing",(V15-K15)/(L15-K15),(K15-V15)/(K15-L15))),"") -> 0.1129922 | X15: =IF(W15="","No Data",IF(W15>=1,"Achieved",IF(W15>=0.5,"On Track","Needs Attention"))) -> Needs Attention | Y15: SSBB Project-Arun Thatoi | Z15: 46246 | AA15: 1.Inser comment
A16: 60 | B16: I | C16: 4924 | D16: Ashok kumar Singh | E16: Unit-III | F16: Industrial Relationship | G16: Increase the Contractual Manpower engagement of Unit-III from ---- per month to 100 % . | H16: Increasing | I16: % | V16: =IFERROR(AVERAGE(M16:S16),"") | W16: =IFERROR(IF(V16="","",IF(H16="Increasing",(V16-K16)/(L16-K16),(K16-V16)/(K16-L16))),"") | X16: =IF(W16="","No Data",IF(W16>=1,"Achieved",IF(W16>=0.5,"On Track","Needs Attention"))) -> No Data | Y16: SSBB Project-Ashok kumar Singh | Z16: 46246 | AA16: 1.Inser comment 2. Issue hopper
A17: 64 | B17: II | C17: 49844 | D17: Ashutosh Pathak | E17: Unit-IV | F17: BE -DRI Operation | G17: Increased Avg Steam generation per day from 162.8 ton to 180 ton K#1 | H17: Increasing | I17: Ton/Day | J17: Sept'25-Dec'25 | K17: 162.8 | L17: 180 | M17: 165.92 | N17: 178.42 | O17: 165.53 | P17: 153.32 | Q17: 158.26 | R17: 142.87 | S17: 161.28 | V17: =IFERROR(AVERAGE(M17:S17),"") -> 160.8 | W17: =IFERROR(IF(V17="","",IF(H17="Increasing",(V17-K17)/(L17-K17),(K17-V17)/(K17-L17))),"") -> -0.11627907 | X17: =IF(W17="","No Data",IF(W17>=1,"Achieved",IF(W17>=0.5,"On Track","Needs Attention"))) -> Needs Attention | Y17: SSBB Project-Ashutosh Pathak | Z17: 46246 | AA17: 1.Inser comment 2. Issue hopper
A18: 65 | B18: II | C18: 49844 | D18: Ashutosh Pathak | E18: Unit-IV | F18: BE -DRI Operation | G18: Increased Avg Steam generation per day from 162.8 ton to 180 ton K#2 | H18: Increasing | I18: Ton/Day | J18: Sept'25-Dec'25 | K18: 162.02 | L18: 180 | M18: 161.66 | N18: 168.45 | O18: 162.94 | P18: 168.89 | Q18: 157.53 | R18: 152.18 | S18: 162 | V18: =IFERROR(AVERAGE(M18:S18),"") -> 161.95 | W18: =IFERROR(IF(V18="","",IF(H18="Increasing",(V18-K18)/(L18-K18),(K18-V18)/(K18-L18))),"") -> -0.0038932147 | X18: =IF(W18="","No Data",IF(W18>=1,"Achieved",IF(W18>=0.5,"On Track","Needs Attention"))) -> Needs Attention | Y18: SSBB Project-Ashutosh Pathak | Z18: 46246 | AA18: Review
A19: 66 | B19: II | C19: 49844 | D19: Ashutosh Pathak | E19: Unit-IV | F19: BE -DRI Operation | G19: Increased Avg Steam generation per day from 172.28 ton to 180 ton K#3 | H19: Increasing | I19: Ton/Day | J19: Sept'25-Dec'25 | K19: 172.28 | L19: 180 | M19: 172.97 | N19: 165.03 | O19: 162.4 | P19: 191.3 | Q19: 189.69 | R19: 179.48 | S19: 155.04 | V19: =IFERROR(AVERAGE(M19:S19),"") -> 173.70143 | W19: =IFERROR(IF(V19="","",IF(H19="Increasing",(V19-K19)/(L19-K19),(K19-V19)/(K19-L19))),"") -> 0.18412287 | X19: =IF(W19="","No Data",IF(W19>=1,"Achieved",IF(W19>=0.5,"On Track","Needs Attention"))) -> Needs Attention | Y19: SSBB Project-Ashutosh Pathak
A20: 67 | B20: II | C20: 49844 | D20: Ashutosh Pathak | E20: Unit-IV | F20: BE -DRI Operation | G20: Increased Avg Steam generation per day from 180.68 ton to 185 ton K#4 | H20: Increasing | I20: Ton/Day | J20: Sept'25-Dec'25 | K20: 180.69 | L20: 185 | M20: 162.62 | N20: 167.1 | O20: 173.41 | P20: 168.54 | Q20: 169.08 | R20: 172.86 | S20: 165.6 | V20: =IFERROR(AVERAGE(M20:S20),"") -> 168.45857 | W20: =IFERROR(IF(V20="","",IF(H20="Increasing",(V20-K20)/(L20-K20),(K20-V20)/(K20-L20))),"") -> -2.8379185 | X20: =IF(W20="","No Data",IF(W20>=1,"Achieved",IF(W20>=0.5,"On Track","Needs Attention"))) -> Needs Attention | Y20: SSBB Project-Ashutosh Pathak | Z20: 46246 | AA20: 1.Inser comment 2. Issue hopper
A21: 53 | B21: I | C21: 80428 | D21: Atish Gupta | E21: Mackeil | F21: Sales & Marketing | G21: Improve on time Delivery of Finished Goods in Mackeil per month from 43 to 56%. | H21: Increasing | I21: % | J21: Apr'25-Sep'25 | K21: 43 | L21: 56 | M21: 41.722924 | N21: 49.878853 | O21: 36.903717 | V21: =IFERROR(AVERAGE(M21:S21),"") -> 42.835165 | W21: =IFERROR(IF(V21="","",IF(H21="Increasing",(V21-K21)/(L21-K21),(K21-V21)/(K21-L21))),"") -> -0.012679644 | X21: =IF(W21="","No Data",IF(W21>=1,"Achieved",IF(W21>=0.5,"On Track","Needs Attention"))) -> Needs Attention | Y21: SSBB Project-Atish Gupta | Z21: 46246 | AA21: 1.Inser comment 2. Issue hopper
A22: 40 | B22: II | C22: 2483 | D22: B.K Mishra | E22: Unit-III | F22: Coke Oven Operation | G22: Reduce the Ash % in Coke of Coke oven plant per month from 12.92 to <12.0 . | H22: Decreasing | I22: % | J22: Jul'25-Dec'25 | K22: 12.92 | L22: 12 | M22: 12.1 | N22: 12.42 | O22: 12.74 | P22: 12.44 | Q22: 12.56 | R22: 12.01 | V22: =IFERROR(AVERAGE(M22:S22),"") -> 12.378333 | W22: =IFERROR(IF(V22="","",IF(H22="Increasing",(V22-K22)/(L22-K22),(K22-V22)/(K22-L22))),"") -> 0.58876812 | X22: =IF(W22="","No Data",IF(W22>=1,"Achieved",IF(W22>=0.5,"On Track","Needs Attention"))) -> On Track | Y22: SSBB Project-B.K Mishra | Z22: 46244 | AA22: 1.Issue hopper 2. Insert comment 3. Aug-26 ( Plan)
A23: 55 | B23: I | C23: 334 | D23: Bidyut Bikash Dinda | E23: Unit-III | F23: Coke Oven Mechanical | G23: Reduce the average monthly general Maintenance Cost per ton of Coke Oven Plant from ₹28.6 to <₹25. | H23: Decreasing | I23: ₹/Ton | J23: Jul'25-Dec'25 | K23: 28.6 | L23: 25 | M23: 24.01 | N23: 21.03 | O23: 24.29 | P23: 25.06 | Q23: 23.67 | R23: 25.262899 | S23: 20.197778 | T23: 20.01 | V23: =IFERROR(AVERAGE(M23:S23),"") -> 23.360097 | W23: =IFERROR(IF(V23="","",IF(H23="Increasing",(V23-K23)/(L23-K23),(K23-V23)/(K23-L23))),"") -> 1.4555287 | X23: =IF(W23="","No Data",IF(W23>=1,"Achieved",IF(W23>=0.5,"On Track","Needs Attention"))) -> Achieved | Y23: SSBB Project-Bidyut Bikash Dinda | Z23: 46244 | AA23: 1.Issue hopper 2. Insert comment 3. Aug-26 ( Plan)
A24: 7 | B24: I | C24: 464 | D24: Binoy Kumar Vishwakarma | E24: Unit-III | F24: Sinter Operation | G24: Reduce the specific energy consumption per ton of sinter from 299887 to <284652 Kcal/TS. | H24: Decreasing | I24: % | J24: Jan'25-Dec'25 | K24: 299887 | L24: 284652 | M24: 308018.8 | N24: 384278.8 | O24: 345679.5 | P24: 309111.7 | Q24: 266104 | R24: 255905.3 | S24: 299720 | T24: 283809.34 | V24: =IFERROR(AVERAGE(M24:S24),"") -> 309831.16 | W24: =IFERROR(IF(V24="","",IF(H24="Increasing",(V24-K24)/(L24-K24),(K24-V24)/(K24-L24))),"") -> -0.6527179 | X24: =IF(W24="","No Data",IF(W24>=1,"Achieved",IF(W24>=0.5,"On Track","Needs Attention"))) -> Needs Attention | Y24: SSBB Project-Binoy Kumar Vishwakarma | Z24: 46244 | AA24: 1.Issue hopper 2. Insert comment 3. Aug-26 ( Plan)
A25: 43 | B25: II | C25: 6095 | D25: Biswanath Banerjee | E25: Unit-III | F25: Drawings and Design | G25: Reduce the Invisible Zn losses of DIP per day from 41.03 gram/m2 to 12.0gram/m2 . | H25: Decreasing | I25: Gram/m2 | J25: Jul'25-Oct'25 | K25: 41.13 | L25: 12 | M25: 11.35 | N25: 11.59 | O25: 9.8 | P25: 13.36 | Q25: 14.36 | R25: 10.49 | S25: 9.39 | T25: 11.79 | V25: =IFERROR(AVERAGE(M25:S25),"") -> 11.477143 | W25: =IFERROR(IF(V25="","",IF(H25="Increasing",(V25-K25)/(L25-K25),(K25-V25)/(K25-L25))),"") -> 1.0179491 | X25: =IF(W25="","No Data",IF(W25>=1,"Achieved",IF(W25>=0.5,"On Track","Needs Attention"))) -> Achieved | Y25: SSBB Project-Biswanath Banerjee | Z25: 46246 | AA25: 1.Insert comment 2. Issue hopper 3. Review Productivity exclude plan shutdown 4. Power failure Action Plan 5. Monsoon Production losses(compare last year data & change the target | AB25: 46260
A26: 47 | B26: I | C26: 48356 | D26: Gourav Sarkar | E26: Unit-IV | F26: BE -RM Operation | G26: Reduce Average Specific Power Consumption of Induction Heater Per Day from 41 to 25. | H26: Decreasing | I26: Kwh/MT | J26: Sep'25-Dec'25 | K26: 34 | L26: 25 | M26: 22 | N26: 22 | O26: 22 | P26: 20 | Q26: 21 | R26: 22 | V26: =IFERROR(AVERAGE(M26:S26),"") -> 21.5 | W26: =IFERROR(IF(V26="","",IF(H26="Increasing",(V26-K26)/(L26-K26),(K26-V26)/(K26-L26))),"") -> 1.3888889 | X26: =IF(W26="","No Data",IF(W26>=1,"Achieved",IF(W26>=0.5,"On Track","Needs Attention"))) -> Achieved | Y26: SSBB Project-Gourav Sarkar | Z26: 46244 | AA26: 1.Inser comment
A27: 41 | B27: I | C27: 49096 | D27: Goutam Patel | E27: Unit-IV | F27: Business Excellence | G27: Reduce the specific power Consumption of Furnace-2 per day from 4251 kWh/MT to 3700 kWh/MT of Ferro Alloys. | H27: Decreasing | I27: Kwh/MT | J27: April-25 -Jan'26 | K27: 4251 | L27: 3700 | N27: 3775.8362 | O27: 4010.5588 | P27: 3850.386 | Q27: 3920.7315 | R27: 3837.6282 | S27: 3832 | V27: =IFERROR(AVERAGE(M27:S27),"") -> 3871.1901 | W27: =IFERROR(IF(V27="","",IF(H27="Increasing",(V27-K27)/(L27-K27),(K27-V27)/(K27-L27))),"") -> 0.68931014 | X27: =IF(W27="","No Data",IF(W27>=1,"Achieved",IF(W27>=0.5,"On Track","Needs Attention"))) -> On Track | Y27: SSBB Project-Goutam Patel | Z27: 46244 | AA27: 1.Inser comment
A28: 9 | B28: II | C28: 7855 | D28: Harsh Sharma | E28: Unit-III | F28: Sinter Mechanical | G28: Reducing Down time per month from 8.77 to < 5 hr for SP1 . | H28: Decreasing | I28: Hrs/month | J28: May'25-Aug'25 | K28: 8.77 | L28: 5 | M28: 7.11 | N28: 5.5 | O28: 6.66 | P28: 11.25 | Q28: 8.08 | R28: 6.08 | S28: 17.33 | T28: 10.75 | V28: =IFERROR(AVERAGE(M28:S28),"") -> 8.8585714 | W28: =IFERROR(IF(V28="","",IF(H28="Increasing",(V28-K28)/(L28-K28),(K28-V28)/(K28-L28))),"") -> -0.023493748 | X28: =IF(W28="","No Data",IF(W28>=1,"Achieved",IF(W28>=0.5,"On Track","Needs Attention"))) -> Needs Attention | Y28: SSBB Project-Harsh Sharma | Z28: 46244 | AA28: 1.Inser comment
A29: 10 | B29: II | C29: 7855 | D29: Harsh Sharma | E29: Unit-III | F29: Sinter Mechanical | G29: Reducing Down time per month from from 6.13 to < 3 hr for SP2. | H29: Decreasing | I29: Hrs/month | J29: May'25-Aug'25 | K29: 6.13 | L29: 3 | M29: 13.5 | N29: 5.2 | O29: 4.58 | P29: 4.83 | Q29: 3.25 | R29: 5.5 | S29: 2.25 | T29: 9.9166667 | V29: =IFERROR(AVERAGE(M29:S29),"") -> 5.5871429 | W29: =IFERROR(IF(V29="","",IF(H29="Increasing",(V29-K29)/(L29-K29),(K29-V29)/(K29-L29))),"") -> 0.17343679 | X29: =IF(W29="","No Data",IF(W29>=1,"Achieved",IF(W29>=0.5,"On Track","Needs Attention"))) -> Needs Attention | Y29: SSBB Project-Harsh Sharma | Z29: 46246 | AA29: 1.Inser comment 2. Issue hopper
A30: 62 | B30: II | C30: 7780 | D30: Hilary Joseph | E30: Unit-III | F30: Industrial Relationship | G30: Reducing Manpower cost /MT 4.58 cr from 3.67 cost/MT | H30: Decreasing | I30: Cost/MT | V30: =IFERROR(AVERAGE(M30:S30),"") | W30: =IFERROR(IF(V30="","",IF(H30="Increasing",(V30-K30)/(L30-K30),(K30-V30)/(K30-L30))),"") | X30: =IF(W30="","No Data",IF(W30>=1,"Achieved",IF(W30>=0.5,"On Track","Needs Attention"))) -> No Data | Y30: SSBB Project-Hilary Joseph | Z30: 46246 | AA30: 1.Inser comment 2. Issue hopper
A31: 51 | B31: II | C31: 5733 | D31: Kalyan Lahiri | E31: Unit-III | F31: Supply Chain Management | G31: Increase the average service cost saving of jai Balaji Industries Ltd Unit-III per month from 17.8 Lakh to 19.58 Lakh. | H31: Increasing | I31: Lakh | K31: 17.8 | L31: 20 | V31: =IFERROR(AVERAGE(M31:S31),"") | W31: =IFERROR(IF(V31="","",IF(H31="Increasing",(V31-K31)/(L31-K31),(K31-V31)/(K31-L31))),"") | X31: =IF(W31="","No Data",IF(W31>=1,"Achieved",IF(W31>=0.5,"On Track","Needs Attention"))) -> No Data | Y31: SSBB Project-Kalyan Lahiri | Z31: 46246 | AA31: 1.Inser comment 2. Issue hopper
A32: 76 | B32: II | C32: 3069 | D32: Kamal Bandyopadhyay | E32: Unit-III | F32: Account | G32: Reduce Avg Planned vs. Actual Cost Variation of the MBF Plantper month from 1449 to 1232. | H32: Decreasing | V32: =IFERROR(AVERAGE(M32:S32),"") | W32: =IFERROR(IF(V32="","",IF(H32="Increasing",(V32-K32)/(L32-K32),(K32-V32)/(K32-L32))),"") | X32: =IF(W32="","No Data",IF(W32>=1,"Achieved",IF(W32>=0.5,"On Track","Needs Attention"))) -> No Data | Y32: SSBB Project-Kamal Bandyopadhyay | Z32: 46246 | AA32: 1.Inser comment 2. Issue hopper
A33: 34 | B33: II | C33: 48820 | D33: Kumar Dipendra | E33: Unit-IV | F33: CPP Operations | G33: Increase Avg BFG Boiler steam Generation Per month from 31.4 TPH to > 33 TPH. | H33: Increasing | I33: TPH | J33: Oct-24-Oct-25 | K33: 31.4 | L33: 33 | M33: 34.565809 | N33: 30.91601 | O33: 31.423077 | P33: 31.47 | Q33: 31.651888 | R33: 31.453333 | S33: 31.597015 | T33: 31.42 | V33: =IFERROR(AVERAGE(M33:S33),"") -> 31.868162 | W33: =IFERROR(IF(V33="","",IF(H33="Increasing",(V33-K33)/(L33-K33),(K33-V33)/(K33-L33))),"") -> 0.2926012 | X33: =IF(W33="","No Data",IF(W33>=1,"Achieved",IF(W33>=0.5,"On Track","Needs Attention"))) -> Needs Attention | Y33: SSBB Project-Kumar Dipendra | Z33: 46246 | AA33: 1.Inser comment 2. Issue hopper 3. Change the Target due to low production | AB33: 46260
A34: 2 | B34: I | C34: 16407 | D34: Manas Mukherjee | E34: Unit-I | F34: Ferro Operations | G34: Increase the Avg Metal recovery(High SiMg) from 83.48% to 90 % for Furnace #1 | H34: Increasing | I34: % | J34: Jan'25-Sept25 | K34: 83.48 | L34: 90 | M34: 87.04 | N34: 86.12 | O34: 86.05 | P34: 85.75 | Q34: 84.3 | V34: =IFERROR(AVERAGE(M34:S34),"") -> 85.852 | W34: =IFERROR(IF(V34="","",IF(H34="Increasing",(V34-K34)/(L34-K34),(K34-V34)/(K34-L34))),"") -> 0.36380368 | X34: =IF(W34="","No Data",IF(W34>=1,"Achieved",IF(W34>=0.5,"On Track","Needs Attention"))) -> Needs Attention | Y34: SSBB Project-Manas Mukherjee | Z34: 46244 | AA34: CTQ to convert Per day and Realing 2. issue hopper
A35: 78 | B35: II | C35: 47561 | D35: Mohammad Ahmad | E35: Unit-IV | F35: Human Resource | G35: Optimize manpower cost of Unit -IV. | H35: Decreasing | V35: =IFERROR(AVERAGE(M35:S35),"") | W35: =IFERROR(IF(V35="","",IF(H35="Increasing",(V35-K35)/(L35-K35),(K35-V35)/(K35-L35))),"") | X35: =IF(W35="","No Data",IF(W35>=1,"Achieved",IF(W35>=0.5,"On Track","Needs Attention"))) -> No Data | Y35: SSBB Project-Mohammad Ahmad | Z35: 46244 | AA35: 1.Issue hopper 2. Insert comment
A36: 8 | B36: II | C36: 6363 | D36: Molay Pan | E36: Unit-III | F36: Coke Oven Electrical | G36: Reduce Specific energy consumption per day of Coke oven plant from 9.36 KWh/Ton to < 8 KWh/Ton . | H36: Decreasing | I36: KWh/Ton | J36: Jan'25 - Dec'25 | K36: 9.36 | L36: 8 | M36: 7.99 | N36: 8.38 | O36: 8.88 | P36: 9.46 | Q36: 9.6 | R36: 11.14 | S36: 10.48 | T36: 9.63 | V36: =IFERROR(AVERAGE(M36:S36),"") -> 9.4185714 | W36: =IFERROR(IF(V36="","",IF(H36="Increasing",(V36-K36)/(L36-K36),(K36-V36)/(K36-L36))),"") -> -0.043067227 | X36: =IF(W36="","No Data",IF(W36>=1,"Achieved",IF(W36>=0.5,"On Track","Needs Attention"))) -> Needs Attention | Y36: SSBB Project-Molay Pan | Z36: 46244 | AA36: 1.Issue hopper 2. Insert comment
A37: 54 | B37: II | D37: Nagendra singh | E37: Unit-III | F37: MBF Operation | G37: Increase the Avg Production of MBF2 per day from 575 Ton to > 650 Ton. | H37: Increasing | I37: Ton/day | J37: Mar-25-Oct-25 | K37: 575 | L37: 650 | M37: 677.51613 | N37: 677.78571 | O37: 648.69231 | P37: 658.82759 | Q37: 638.47059 | R37: 632.54167 | V37: =IFERROR(AVERAGE(M37:S37),"") -> 655.639 | W37: =IFERROR(IF(V37="","",IF(H37="Increasing",(V37-K37)/(L37-K37),(K37-V37)/(K37-L37))),"") -> 1.0751866 | X37: =IF(W37="","No Data",IF(W37>=1,"Achieved",IF(W37>=0.5,"On Track","Needs Attention"))) -> Achieved | Y37: SSBB Project-Nagendra singh | Z37: 46244 | AA37: 1.Issue hopper 2. Insert comment
A38: 44 | B38: I | C38: 6323 | D38: Nagesh Kumar | E38: Unit-III | F38: DIP Electrical | G38: Reduce the specific power consumption of DIP Compressor from 52.83 KWH/MT to 35 KWH/MT per day. | H38: Decreasing | I38: Kwh/MT | J38: Augt'25-Nov'25 | K38: 38.75 | L38: 35 | M38: 20 | N38: 23 | O38: 24 | P38: 29 | Q38: 28 | R38: 25 | S38: 29 | T38: 31.006 | U38: 22.756 | V38: =IFERROR(AVERAGE(M38:S38),"") -> 25.428571 | W38: =IFERROR(IF(V38="","",IF(H38="Increasing",(V38-K38)/(L38-K38),(K38-V38)/(K38-L38))),"") -> 3.552381 | X38: =IF(W38="","No Data",IF(W38>=1,"Achieved",IF(W38>=0.5,"On Track","Needs Attention"))) -> Achieved | Y38: SSBB Project-Nagesh Kumar | Z38: 46244 | AA38: 1.Issue hopper 2. Insert comment
A39: 48 | B39: II | C39: 5612 | D39: Nilesh Rathaur | E39: Unit-III | F39: Safety | G39: Reducing Mandays loss of Jai Balaji Unit-3 from 1546 per month to 600 per /month | H39: Decreasing | I39: Days | J39: Jun'24-Dec'25 | K39: 1411 | L39: 1000 | M39: 1591 | N39: 1637 | O39: 1108 | P39: 34 | Q39: 87 | R39: 139 | V39: =IFERROR(AVERAGE(M39:S39),"") -> 766 | W39: =IFERROR(IF(V39="","",IF(H39="Increasing",(V39-K39)/(L39-K39),(K39-V39)/(K39-L39))),"") -> 1.5693431 | X39: =IF(W39="","No Data",IF(W39>=1,"Achieved",IF(W39>=0.5,"On Track","Needs Attention"))) -> Achieved | Y39: SSBB Project-Manoj Kumar
A40: 49 | B40: II | C40: 8216 | D40: Pankaj Dubey | E40: Unit-III | F40: Human Resource | G40: Reducing LWP per month from 3.10 to <2%. | H40: Decreasing | I40: % | J40: Jan'25-Sep'25 | K40: 3.1 | L40: 2 | M40: 0.93194136 | N40: 1.4 | O40: 1.7 | P40: 2.1 | Q40: 2.2 | R40: 2.1 | V40: =IFERROR(AVERAGE(M40:S40),"") -> 1.7386569 | W40: =IFERROR(IF(V40="","",IF(H40="Increasing",(V40-K40)/(L40-K40),(K40-V40)/(K40-L40))),"") -> 1.2375846 | X40: =IF(W40="","No Data",IF(W40>=1,"Achieved",IF(W40>=0.5,"On Track","Needs Attention"))) -> Achieved | Y40: SSBB Project-Pankaj Dubey | Z40: 46246 | AA40: 1.Data to be change 2. Issu hopper
A41: 35 | B41: I | C41: 45833 | D41: Papan Nayak | E41: Unit-IV | F41: CPP Operations | G41: Reduce the Avg Steam loss of Power Plant per month from 8895 to 2261 ton. | H41: Decreasing | I41: Ton/Month | J41: Dec'24-Oct25 | K41: 8894 | L41: 2261 | M41: 859 | N41: 528 | O41: 550 | P41: 371 | Q41: 390 | R41: 586 | S41: 981 | V41: =IFERROR(AVERAGE(M41:S41),"") -> 609.28571 | W41: =IFERROR(IF(V41="","",IF(H41="Increasing",(V41-K41)/(L41-K41),(K41-V41)/(K41-L41))),"") -> 1.2490147 | X41: =IF(W41="","No Data",IF(W41>=1,"Achieved",IF(W41>=0.5,"On Track","Needs Attention"))) -> Achieved | Y41: SSBB Project-Papan Nayak | Z41: 46244 | AA41: 1.Issue hopper 2. Insert comment
A42: 63 | B42: II | C42: 9517 | D42: PK Swain | E42: Unit-IV | F42: Electrical | G42: Improving power factor from ------- to -------- in Unit -IV. | H42: Increasing | V42: =IFERROR(AVERAGE(M42:S42),"") | W42: =IFERROR(IF(V42="","",IF(H42="Increasing",(V42-K42)/(L42-K42),(K42-V42)/(K42-L42))),"") | X42: =IF(W42="","No Data",IF(W42>=1,"Achieved",IF(W42>=0.5,"On Track","Needs Attention"))) -> No Data | Y42: SSBB Project-PK Swain
A43: 45 | B43: I | C43: 10952 | D43: Prakash Joshi | E43: Unit-III | F43: Human Resource | G43: Manpower cost optimization per month from 7.04 cr to 6.8 cr of Unit-III. | H43: Decreasing | I43: Crore | J43: June-25-Sept'25 | K43: 7.04 | L43: 6.8 | M43: 6.41 | N43: 6.7 | O43: 6.9875934 | P43: 7.1282524 | Q43: 7.1052879 | R43: 7.1717641 | S43: 7.1938758 | V43: =IFERROR(AVERAGE(M43:S43),"") -> 6.9566819 | W43: =IFERROR(IF(V43="","",IF(H43="Increasing",(V43-K43)/(L43-K43),(K43-V43)/(K43-L43))),"") -> 0.34715857 | X43: =IF(W43="","No Data",IF(W43>=1,"Achieved",IF(W43>=0.5,"On Track","Needs Attention"))) -> Needs Attention | Y43: SSBB Project-Prakash Joshi | Z43: 46244 | AA43: 1.Issue hopper 2. Insert comment
A44: 56 | B44: II | C44: 7747 | D44: Prasanta Basu | E44: Unit-III | F44: ISO | G44: Reduction of Paper Consumption through Effective IMS Internal Audits & Competence-Based Training from 27620 to < 5524. | H44: Decreasing | I44: Nos | J44: Jan'23-Jan'25 | K44: 27620 | L44: 5524 | V44: =IFERROR(AVERAGE(M44:S44),"") | W44: =IFERROR(IF(V44="","",IF(H44="Increasing",(V44-K44)/(L44-K44),(K44-V44)/(K44-L44))),"") | X44: =IF(W44="","No Data",IF(W44>=1,"Achieved",IF(W44>=0.5,"On Track","Needs Attention"))) -> No Data | Y44: SSBB Project-Prasanta Basu
A45: 11 | B45: II | C45: 7448 | D45: Prasanta Karmakar | E45: Unit-III | F45: RMHS Operation | G45: Increase the average monthly efficiency of Iron ore Washery Plant-1 from 77.25 % to >85%. | H45: Increasing | I45: % | J45: Apr'25-Sept-25 | K45: 77.25 | L45: 85 | M45: 95.1 | N45: 92.24 | O45: 87.6 | P45: 86.11 | Q45: 96.05 | R45: 90.87 | S45: 79.736842 | T45: 75.555556 | V45: =IFERROR(AVERAGE(M45:S45),"") -> 89.672406 | W45: =IFERROR(IF(V45="","",IF(H45="Increasing",(V45-K45)/(L45-K45),(K45-V45)/(K45-L45))),"") -> 1.6028911 | X45: =IF(W45="","No Data",IF(W45>=1,"Achieved",IF(W45>=0.5,"On Track","Needs Attention"))) -> Achieved | Y45: SSBB Project-Prasanta Karmakar
A46: 12 | B46: II | C46: 7448 | D46: Prasanta Karmakar | E46: Unit-III | F46: RMHS Operation | G46: Increase the average monthly efficiency of Iron ore Washery Plant-2 from 78.26 % to >85% | H46: Increasing | I46: % | J46: Apr'25-Sept-25 | K46: 78.26 | L46: 85 | M46: 91.61 | N46: 94.07 | O46: 95.7 | P46: 95.96 | Q46: 96.46 | R46: 96.48 | S46: 96.287879 | T46: 97.44 | V46: =IFERROR(AVERAGE(M46:S46),"") -> 95.223983 | W46: =IFERROR(IF(V46="","",IF(H46="Increasing",(V46-K46)/(L46-K46),(K46-V46)/(K46-L46))),"") -> 2.5169114 | X46: =IF(W46="","No Data",IF(W46>=1,"Achieved",IF(W46>=0.5,"On Track","Needs Attention"))) -> Achieved | Y46: SSBB Project-Prasanta Karmakar | Z46: 46246 | AA46: 1.Insert comment 2 Issue hopper
A47: 77 | B47: II | D47: Prashnat Yadav | E47: Mackeil | F47: Estimation | G47: To Increased PO Conversation Ratio | H47: Increasing | V47: =IFERROR(AVERAGE(M47:S47),"") | W47: =IFERROR(IF(V47="","",IF(H47="Increasing",(V47-K47)/(L47-K47),(K47-V47)/(K47-L47))),"") | X47: =IF(W47="","No Data",IF(W47>=1,"Achieved",IF(W47>=0.5,"On Track","Needs Attention"))) -> No Data | Y47: SSBB Project-Prashnat Yadav | Z47: 46244 | AA47: 1.Issue hopper 2. Insert comment
A48: 46 | B48: II | C48: 50360 | D48: Pratip Roy | E48: Unit-IV | F48: Business Excellence | G48: Reducing the average return fines of BQT plant per day from 17.76 % to < 15 %. | H48: Decreasing | I48: % | J48: Oct-25 - Mar- 26 | K48: 17.76 | L48: 15 | P48: 20.32 | Q48: 23.27 | R48: 21.27 | V48: =IFERROR(AVERAGE(M48:S48),"") -> 21.62 | W48: =IFERROR(IF(V48="","",IF(H48="Increasing",(V48-K48)/(L48-K48),(K48-V48)/(K48-L48))),"") -> -1.3985507 | X48: =IF(W48="","No Data",IF(W48>=1,"Achieved",IF(W48>=0.5,"On Track","Needs Attention"))) -> Needs Attention | Y48: SSBB Project-Pratip Roy | Z48: 46246 | AA48: 1. All furnace
A49: 24 | B49: II | C49: 4382 | D49: Prithwis Bhattacharya | E49: Unit-III | F49: DIP Mechanical | G49: To reduce the frequency of downtime per month in M/C 5 from 56 to 46 respectively i.e increase MTBF without increase MTTR. | H49: Decreasing | I49: Nos. | J49: Nov'24-Oct'25 | K49: 56 | L49: 46 | M49: 32 | N49: 14 | O49: 45 | Q49: 80 | R49: 50 | V49: =IFERROR(AVERAGE(M49:S49),"") -> 44.2 | W49: =IFERROR(IF(V49="","",IF(H49="Increasing",(V49-K49)/(L49-K49),(K49-V49)/(K49-L49))),"") -> 1.18 | X49: =IF(W49="","No Data",IF(W49>=1,"Achieved",IF(W49>=0.5,"On Track","Needs Attention"))) -> Achieved | Y49: SSBB Project-Prithwis Bhattacharya | Z49: 46246 | AA49: 1.Insert comment 2. Issue hopper & add the project
A50: 25 | B50: II | C50: 4382 | D50: Prithwis Bhattacharya | E50: Unit-III | F50: DIP Mechanical | G50: To reduce the frequency of downtime per month in M/C 6 from 54 to 44 respectively i.e increase MTBF without increase MTTR. | H50: Decreasing | I50: Nos. | J50: Nov'24-Oct'25 | K50: 54 | L50: 44 | M50: 44 | N50: 34 | O50: 36 | P50: 33 | Q50: 47 | R50: 55 | V50: =IFERROR(AVERAGE(M50:S50),"") -> 41.5 | W50: =IFERROR(IF(V50="","",IF(H50="Increasing",(V50-K50)/(L50-K50),(K50-V50)/(K50-L50))),"") -> 1.25 | X50: =IF(W50="","No Data",IF(W50>=1,"Achieved",IF(W50>=0.5,"On Track","Needs Attention"))) -> Achieved | Y50: SSBB Project-Prithwis Bhattacharya | Z50: 46244 | AA50: 1.Issue hopper 2. Insert comment
A51: 26 | B51: II | C51: 4382 | D51: Prithwis Bhattacharya | E51: Unit-III | F51: DIP Mechanical | G51: To reduce the frequency of downtime per month in M/C 7A from 81 to 60 respectively i.e increase MTBF without increase MTTR. | H51: Decreasing | I51: Nos. | J51: Nov'24-Oct'25 | K51: 81 | L51: 60 | M51: 62 | N51: 50 | O51: 65 | P51: 89 | Q51: 91 | R51: 34 | V51: =IFERROR(AVERAGE(M51:S51),"") -> 65.166667 | W51: =IFERROR(IF(V51="","",IF(H51="Increasing",(V51-K51)/(L51-K51),(K51-V51)/(K51-L51))),"") -> 0.75396825 | X51: =IF(W51="","No Data",IF(W51>=1,"Achieved",IF(W51>=0.5,"On Track","Needs Attention"))) -> On Track | Y51: SSBB Project-Prithwis Bhattacharya | Z51: 46244 | AA51: 1.Issue hopper 2. Insert comment
A52: 27 | B52: II | C52: 4382 | D52: Prithwis Bhattacharya | E52: Unit-III | F52: DIP Mechanical | G52: To reduce the frequency of downtime per month in M/C 9 from 74 to 50 respectively i.e increase MTBF without increase MTTR. | H52: Decreasing | I52: Nos. | J52: Nov'24-Oct'25 | K52: 74 | L52: 50 | M52: 21 | N52: 28 | O52: 55 | P52: 19 | Q52: 57 | R52: 50 | V52: =IFERROR(AVERAGE(M52:S52),"") -> 38.333333 | W52: =IFERROR(IF(V52="","",IF(H52="Increasing",(V52-K52)/(L52-K52),(K52-V52)/(K52-L52))),"") -> 1.4861111 | X52: =IF(W52="","No Data",IF(W52>=1,"Achieved",IF(W52>=0.5,"On Track","Needs Attention"))) -> Achieved | Y52: SSBB Project-Prithwis Bhattacharya
A53: 20 | B53: II | C53: 7313 | D53: Pushpendra Ganguly | E53: Unit-III | F53: MBF Operation | G53: Increase the Avg Productivity of MBF2 per day from 3.46 Ton/m3 to >3.606 Ton/m3 . | H53: Increasing | I53: Ton/day/m3 | J53: Aug'25-Dec'25 | K53: 3.46 | L53: 3.606 | M53: 3.408 | N53: 3.395 | O53: 3.424 | P53: 3.5219 | Q53: 3.496 | R53: 3.51 | S53: 3.5513 | T53: 3.5227 | V53: =IFERROR(AVERAGE(M53:S53),"") -> 3.4723143 | W53: =IFERROR(IF(V53="","",IF(H53="Increasing",(V53-K53)/(L53-K53),(K53-V53)/(K53-L53))),"") -> 0.084344423 | X53: =IF(W53="","No Data",IF(W53>=1,"Achieved",IF(W53>=0.5,"On Track","Needs Attention"))) -> Needs Attention | Y53: SSBB Project-Pushpendra Ganguly | Z53: 46244 | AA53: 1.Issue hopper 2. Insert comment
A54: 3 | B54: I | C54: 4 | D54: Ravindra Kumar Meherwal | E54: Unit-III | F54: Central Electrical | G54: Increase the Avg Load factor of LCFC per month(for furnace 1 to 5) from 0.78 to 0.83. | H54: Increasing | I54: Load Factor | J54: Jul'25-Oct'25 | K54: 0.78 | L54: 0.83 | M54: 0.79 | N54: 0.73 | O54: 0.80298469 | P54: 0.77706842 | Q54: 0.79189895 | R54: 0.73794202 | V54: =IFERROR(AVERAGE(M54:S54),"") -> 0.77164901 | W54: =IFERROR(IF(V54="","",IF(H54="Increasing",(V54-K54)/(L54-K54),(K54-V54)/(K54-L54))),"") -> -0.16701974 | X54: =IF(W54="","No Data",IF(W54>=1,"Achieved",IF(W54>=0.5,"On Track","Needs Attention"))) -> Needs Attention | Y54: SSBB Project-Ravindra Kumar Meherwal
A55: 74 | B55: I | C55: 10811 | D55: Roopam Rai | E55: HO | F55: Business Excellence | G55: Development of New Products with High Demand for Open Die Forgings Plant". | H55: Increasing | V55: =IFERROR(AVERAGE(M55:S55),"") | W55: =IFERROR(IF(V55="","",IF(H55="Increasing",(V55-K55)/(L55-K55),(K55-V55)/(K55-L55))),"") | X55: =IF(W55="","No Data",IF(W55>=1,"Achieved",IF(W55>=0.5,"On Track","Needs Attention"))) -> No Data | Y55: SSBB Project-Roopam Rai | AA55: 1.Over time 2.Man power requirement per ton 3.
A56: 14 | B56: II | C56: 48956 | D56: Sailesh Singh Yadav | E56: Unit-IV | F56: Operation | G56: Cr Recovery from 87 % to > 90% ( Grade - Cr-60 & C-0.50 %) in Ferro alloys division in AOD | H56: Increasing | I56: % | J56: Augt'25-Dec'25 | K56: 87 | L56: 90 | V56: =IFERROR(AVERAGE(M56:S56),"") | W56: =IFERROR(IF(V56="","",IF(H56="Increasing",(V56-K56)/(L56-K56),(K56-V56)/(K56-L56))),"") | X56: =IF(W56="","No Data",IF(W56>=1,"Achieved",IF(W56>=0.5,"On Track","Needs Attention"))) -> No Data | Y56: SSBB Project-Sailesh Singh Yadav
A57: 15 | B57: II | C57: 48956 | D57: Sailesh Singh Yadav | E57: Unit-IV | F57: Operation | G57: Cr Recovery from 87 % to > 90% ( Grade - Cr-60 & C-5 %) in Ferro alloys division in AOD | H57: Increasing | I57: % | J57: Augt'25-Dec'25 | K57: 88.79 | L57: 90 | N57: 86.16 | O57: 84.35 | R57: 83.39 | S57: 80.25 | T57: 86.3 | V57: =IFERROR(AVERAGE(M57:S57),"") -> 83.5375 | W57: =IFERROR(IF(V57="","",IF(H57="Increasing",(V57-K57)/(L57-K57),(K57-V57)/(K57-L57))),"") -> -4.3409091 | X57: =IF(W57="","No Data",IF(W57>=1,"Achieved",IF(W57>=0.5,"On Track","Needs Attention"))) -> Needs Attention | Y57: SSBB Project-Sailesh Singh Yadav
A58: 16 | B58: II | C58: 48956 | D58: Sailesh Singh Yadav | E58: Unit-IV | F58: Operation | G58: Cr Recovery from 87 % to > 90%( Grade - Cr-66 & C-0.75 %) in Ferro alloys division in AOD | H58: Increasing | I58: % | J58: Oct'25-Dec'25 | K58: 86.53 | L58: 90 | M58: 87.19 | N58: 90.3 | O58: 90.17 | Q58: 90.89 | S58: 91.23 | T58: 87.71 | V58: =IFERROR(AVERAGE(M58:S58),"") -> 89.956 | W58: =IFERROR(IF(V58="","",IF(H58="Increasing",(V58-K58)/(L58-K58),(K58-V58)/(K58-L58))),"") -> 0.98731988 | X58: =IF(W58="","No Data",IF(W58>=1,"Achieved",IF(W58>=0.5,"On Track","Needs Attention"))) -> On Track | Y58: SSBB Project-Sailesh Singh Yadav | Z58: 46244 | AA58: Project to be change
A59: 21 | B59: I | C59: 0 | D59: Samanway Das | E59: Unit-III | F59: MBF Operation | G59: Reduce the Fuel consumption of Blast furnace 2 per day from 613 Kg/THM to 550 Kg/THM. | H59: Decreasing | I59: Kg/THM | J59: Jul'25-Dec'25 | K59: 613 | L59: 550 | M59: 627.37032 | N59: 609.07143 | O59: 604.26667 | P59: 596.83333 | Q59: 610.33575 | R59: 592.04352 | S59: 593 | T59: 595 | V59: =IFERROR(AVERAGE(M59:S59),"") -> 604.703 | W59: =IFERROR(IF(V59="","",IF(H59="Increasing",(V59-K59)/(L59-K59),(K59-V59)/(K59-L59))),"") -> 0.13169836 | X59: =IF(W59="","No Data",IF(W59>=1,"Achieved",IF(W59>=0.5,"On Track","Needs Attention"))) -> Needs Attention | Y59: SSBB Project-Samanway Das
A60: 22 | B60: I | D60: Samanway Das | E60: Unit-III | F60: MBF Operation | G60: Reduce coke Rate of Blast furnace 2 per day from 492 Kg/THM to 400 Kg/THM. | H60: Decreasing | I60: Kg/THM | J60: Jul'25-Dec'25 | K60: 492 | L60: 400 | M60: 528.6129 | N60: 508.78571 | O60: 483.53333 | P60: 476.96667 | Q60: 488.42205 | R60: 451.01637 | S60: 460 | T60: 461 | V60: =IFERROR(AVERAGE(M60:S60),"") -> 485.33386 | W60: =IFERROR(IF(V60="","",IF(H60="Increasing",(V60-K60)/(L60-K60),(K60-V60)/(K60-L60))),"") -> 0.072458006 | X60: =IF(W60="","No Data",IF(W60>=1,"Achieved",IF(W60>=0.5,"On Track","Needs Attention"))) -> Needs Attention | Y60: SSBB Project-Samanway Das | Z60: 46246 | AA60: 1.Insert comment
A61: 23 | B61: I | D61: Samanway Das | E61: Unit-III | F61: MBF Operation | G61: Increase coal Injection Rate of Blast furnace 2 per day from 118 Kg/THM to 150Kg/THM. | H61: Increasing | I61: Kg/THM | J61: Jul'25-Dec'25 | K61: 118 | L61: 150 | M61: 98.757419 | N61: 100.28571 | O61: 120.73333 | P61: 119.86667 | Q61: 121.91369 | R61: 141.02715 | S61: 133 | T61: 134 | V61: =IFERROR(AVERAGE(M61:S61),"") -> 119.36914 | W61: =IFERROR(IF(V61="","",IF(H61="Increasing",(V61-K61)/(L61-K61),(K61-V61)/(K61-L61))),"") -> 0.042785615 | X61: =IF(W61="","No Data",IF(W61>=1,"Achieved",IF(W61>=0.5,"On Track","Needs Attention"))) -> Needs Attention | Y61: SSBB Project-Samanway Das
A62: 4 | B62: I | C62: 10818 | D62: Sandip Sil ,A.P Sahoo,Sudipta Chatterjee,Ashish Ranjan | E62: Unit-III | F62: DIP Operation | G62: Reducing over all rejection of DIP from 9.9 % to 6.90 % . | H62: Decreasing | I62: % | J62: Dec'24-Oct'25 | K62: 9.9 | L62: 6.9 | M62: 7.03 | N62: 6.83 | O62: 8.12 | P62: 9.38 | Q62: 9.96 | R62: 8.34 | S62: 7.41 | V62: =IFERROR(AVERAGE(M62:S62),"") -> 8.1528571 | W62: =IFERROR(IF(V62="","",IF(H62="Increasing",(V62-K62)/(L62-K62),(K62-V62)/(K62-L62))),"") -> 0.58238095 | X62: =IF(W62="","No Data",IF(W62>=1,"Achieved",IF(W62>=0.5,"On Track","Needs Attention"))) -> On Track | Y62: SSBB Project -Sandip Sil, Ambika Sahoo | Z62: 46246 | AA62: 1. Non conformance (External) 2.Customer complain 3.Add project
A63: 5 | B63: I | C63: 4939 | D63: Sandipan Ghosh | E63: Unit-III | F63: RMHS Electrical | G63: Increase the average plant availability of Iron Ore Washery from 84.48 % per day to >90% for IOW-1 . | H63: Increasing | I63: % | J63: Apr'25-Oct'25 | K63: 84.48 | L63: 90 | M63: 97.037037 | N63: 81.458333 | O63: 73.888889 | P63: 86.923077 | Q63: 86.555556 | R63: 93.32 | S63: 95.833333 | T63: 76.981481 | V63: =IFERROR(AVERAGE(M63:S63),"") -> 87.859461 | W63: =IFERROR(IF(V63="","",IF(H63="Increasing",(V63-K63)/(L63-K63),(K63-V63)/(K63-L63))),"") -> 0.61222115 | X63: =IF(W63="","No Data",IF(W63>=1,"Achieved",IF(W63>=0.5,"On Track","Needs Attention"))) -> On Track | Y63: SSBB Project-Sandipan Ghosh
A64: 6 | B64: I | C64: 4939 | D64: Sandipan Ghosh | E64: Unit-III | F64: RMHS Electrical | G64: Increase the average plant availability of Iron Ore Washery from 81.70% per day to >90% for IOW-2. | H64: Increasing | I64: % | J64: Apr'25-Oct'25 | K64: 81.77 | L64: 90 | M64: 99.722222 | N64: 95.264583 | O64: 98.975926 | P64: 95.630769 | Q64: 96.611111 | R64: 99.390385 | S64: 99.62963 | T64: 98.5 | V64: =IFERROR(AVERAGE(M64:S64),"") -> 97.889232 | W64: =IFERROR(IF(V64="","",IF(H64="Increasing",(V64-K64)/(L64-K64),(K64-V64)/(K64-L64))),"") -> 1.9585944 | X64: =IF(W64="","No Data",IF(W64>=1,"Achieved",IF(W64>=0.5,"On Track","Needs Attention"))) -> Achieved | Y64: SSBB Project-Sandipan Ghosh | AA64: 1.No of Sample 2. Deviation
A65: 17 | B65: I | C65: 49269 | D65: Sanjay Nayak | E65: Unit-IV | F65: Ferro Operations | G65: Average the Cr recovery of Furnace -1 84.53 % per month 88.0 % per Month | H65: Increasing | I65: % | J65: Sept'25 - Dec'25 | K65: 84.53 | L65: 88 | M65: 85.3 | N65: 86.08 | O65: 84.1 | P65: 81.44 | Q65: 84.68 | R65: 85.038333 | S65: 82.817667 | V65: =IFERROR(AVERAGE(M65:S65),"") -> 84.208 | W65: =IFERROR(IF(V65="","",IF(H65="Increasing",(V65-K65)/(L65-K65),(K65-V65)/(K65-L65))),"") -> -0.092795389 | X65: =IF(W65="","No Data",IF(W65>=1,"Achieved",IF(W65>=0.5,"On Track","Needs Attention"))) -> Needs Attention | Y65: SSBB Project-Sanjay Nayak
A66: 18 | B66: I | C66: 49269 | D66: Sanjay Nayak | E66: Unit-IV | F66: Ferro Operations | G66: Average the Cr recovery of Furnace -2 80.23 % per month 85.0 % per Month | H66: Increasing | I66: % | J66: Sept'25 - Dec'25 | K66: 80.23 | L66: 85 | M66: 76.27 | N66: 84.1 | O66: 79.73 | P66: 83.02 | Q66: 82.88 | R66: 90.060667 | S66: 84.777097 | V66: =IFERROR(AVERAGE(M66:S66),"") -> 82.976823 | W66: =IFERROR(IF(V66="","",IF(H66="Increasing",(V66-K66)/(L66-K66),(K66-V66)/(K66-L66))),"") -> 0.57585395 | X66: =IF(W66="","No Data",IF(W66>=1,"Achieved",IF(W66>=0.5,"On Track","Needs Attention"))) -> On Track | Y66: SSBB Project-Sanjay Nayak
A67: 19 | B67: I | C67: 49269 | D67: Sanjay Nayak | E67: Unit-IV | F67: Ferro Operations | G67: Average the Cr recovery of Furnace -III 87.83 % per month 90.0 % per Month | H67: Increasing | I67: % | J67: Sept'25 - Dec'25 | K67: 87.83 | L67: 90 | M67: 87.7 | N67: 87.18 | O67: 84.24 | P67: 83.85 | Q67: 86.15 | R67: 74.461667 | S67: 88.493226 | V67: =IFERROR(AVERAGE(M67:S67),"") -> 84.582127 | W67: =IFERROR(IF(V67="","",IF(H67="Increasing",(V67-K67)/(L67-K67),(K67-V67)/(K67-L67))),"") -> -1.4967154 | X67: =IF(W67="","No Data",IF(W67>=1,"Achieved",IF(W67>=0.5,"On Track","Needs Attention"))) -> Needs Attention | Y67: SSBB Project-Sanjay Nayak
A68: 72 | B68: I | D68: Sanjib Pattnaik | E68: UNIT-I | F68: Human Resource | H68: Decreasing | V68: =IFERROR(AVERAGE(M68:S68),"") | W68: =IFERROR(IF(V68="","",IF(H68="Increasing",(V68-K68)/(L68-K68),(K68-V68)/(K68-L68))),"") | X68: =IF(W68="","No Data",IF(W68>=1,"Achieved",IF(W68>=0.5,"On Track","Needs Attention"))) -> No Data | Y68: SSBB Project-Sanjib Pattnaik
A69: 38 | B69: II | C69: 4837 | D69: Sashank Shekhar | E69: Unit-III | F69: MBF-Mechanical | G69: Increased Productivity of Pig Casting Machine -1 (Double Strand) | H69: Increasing | I69: MT/Day | J69: 2026-06-01 00:00:00 | K69: 572 | L69: 800 | V69: =IFERROR(AVERAGE(M69:S69),"") | W69: =IFERROR(IF(V69="","",IF(H69="Increasing",(V69-K69)/(L69-K69),(K69-V69)/(K69-L69))),"") | X69: =IF(W69="","No Data",IF(W69>=1,"Achieved",IF(W69>=0.5,"On Track","Needs Attention"))) -> No Data | Y69: SSBB Project-Sashank Shekhar
A70: 39 | B70: II | C70: 4837 | D70: Sashank Shekhar | E70: Unit-III | F70: MBF-Mechanical | G70: Increased Productivity of Pig Casting Machine -2 (Double Stand) | H70: Increasing | I70: MT/Day | J70: 2026-06-01 00:00:00 | K70: 520 | L70: 800 | R70: 528 | V70: =IFERROR(AVERAGE(M70:S70),"") -> 528 | W70: =IFERROR(IF(V70="","",IF(H70="Increasing",(V70-K70)/(L70-K70),(K70-V70)/(K70-L70))),"") -> 0.028571429 | X70: =IF(W70="","No Data",IF(W70>=1,"Achieved",IF(W70>=0.5,"On Track","Needs Attention"))) -> Needs Attention | Y70: SSBB Project-Sashank Shekhar | Z70: 46244 | AA70: 1.Issue hopper 2. Insert comment
A71: 29 | B71: I | D71: Shantimoy Som | E71: Unit-III | F71: Coke Oven | G71: Increase Avg steam of WHRB plant through coke Gas from 1480Ton/day to >1704 Ton/day . | H71: Increasing | I71: MT/Month | J71: Oct24-Sep'25 | K71: 1480 | L71: 1704 | M71: 1917.9871 | N71: 1765.4918 | O71: 1567.6714 | P71: 1759.592 | Q71: 1889.729 | R71: 1832.4 | S71: 1842.929 | T71: 1795 | U71: 1709 | V71: =IFERROR(AVERAGE(M71:S71),"") -> 1796.5429 | W71: =IFERROR(IF(V71="","",IF(H71="Increasing",(V71-K71)/(L71-K71),(K71-V71)/(K71-L71))),"") -> 1.413138 | X71: =IF(W71="","No Data",IF(W71>=1,"Achieved",IF(W71>=0.5,"On Track","Needs Attention"))) -> Achieved | Y71: SSBB Project-Shantimoy Som | Z71: 46244 | AA71: 1.Issue hopper 2. Insert comment
A72: 68 | B72: II | C72: 48624 | D72: Sidheswar Biswal | E72: Unit-IV | F72: Safety | G72: Reducing unsafe condition per months from 406 to < 203. | H72: Decreasing | I72: Nos | V72: =IFERROR(AVERAGE(M72:S72),"") | W72: =IFERROR(IF(V72="","",IF(H72="Increasing",(V72-K72)/(L72-K72),(K72-V72)/(K72-L72))),"") | X72: =IF(W72="","No Data",IF(W72>=1,"Achieved",IF(W72>=0.5,"On Track","Needs Attention"))) -> No Data | Y72: SSBB Project-Sidheswar Biswal | Z72: 46244 | AA72: 1.Issue hopper 2. Insert comment
A73: 61 | B73: II | C73: 50618 | D73: Sohel Rana | E73: Unit-IV | F73: Business Excellence | G73: Breakdown reduction in rolling Mill #2 from 15.03 % to <10.0% | H73: Decreasing | I73: % | J73: Oct'25-Dec'25 | K73: 15.03 | L73: 10 | M73: 8.14 | N73: 6.3 | O73: 6.8 | P73: 5.5 | Q73: 11.18 | R73: 7.63 | V73: =IFERROR(AVERAGE(M73:S73),"") -> 7.5916667 | W73: =IFERROR(IF(V73="","",IF(H73="Increasing",(V73-K73)/(L73-K73),(K73-V73)/(K73-L73))),"") -> 1.4787939 | X73: =IF(W73="","No Data",IF(W73>=1,"Achieved",IF(W73>=0.5,"On Track","Needs Attention"))) -> Achieved | Y73: SSBB Project-Sohel Rana | Z73: 46244 | AA73: 1.Issue hopper 2. Insert comment
A74: 28 | B74: II | C74: 5152 | D74: Somnath Patra | E74: Unit-III | F74: Sinter Electrical | G74: Reduce the Specific Power Consumption of Sinter Plant 1 from 52.99 kWh/MT to <45 kWh/MT per day. | H74: Decreasing | I74: kWh/Ton | J74: Aug'25-Nov'25 | K74: 52.989 | L74: 45 | M74: 49.72 | N74: 61.39 | O74: 56.93 | P74: 49.46 | Q74: 53.22 | R74: 57.65 | S74: 46 | V74: =IFERROR(AVERAGE(M74:S74),"") -> 53.481429 | W74: =IFERROR(IF(V74="","",IF(H74="Increasing",(V74-K74)/(L74-K74),(K74-V74)/(K74-L74))),"") -> -0.061638324 | X74: =IF(W74="","No Data",IF(W74>=1,"Achieved",IF(W74>=0.5,"On Track","Needs Attention"))) -> Needs Attention | Y74: SSBB Project-Somnath Patra
B75: II | C75: 5152 | D75: Somnath Patra | E75: Unit-III | F75: Sinter Electrical | G75: Production volume of sinter plant-1
A76: 71 | B76: II | C76: 11039 | D76: Soumen Pal | E76: HO | F76: DIP Marketing | G76: Re-establish the tendor data base (tendor missing) per month from -------to ----. | H76: Increasing | I76: Nos | V76: =IFERROR(AVERAGE(M76:S76),"") | W76: =IFERROR(IF(V76="","",IF(H76="Increasing",(V76-K76)/(L76-K76),(K76-V76)/(K76-L76))),"") | X76: =IF(W76="","No Data",IF(W76>=1,"Achieved",IF(W76>=0.5,"On Track","Needs Attention"))) -> No Data | Y76: SSBB Project-Soumen Pal
A77: 70 | B77: II | C77: 10860 | D77: Souptik Mondal | E77: HO | F77: DIP Marketing | G77: Reducing the freight cost per Km /MT from 580 to <----. | I77: Per kM/MT | V77: =IFERROR(AVERAGE(M77:S77),"") | W77: =IFERROR(IF(V77="","",IF(H77="Increasing",(V77-K77)/(L77-K77),(K77-V77)/(K77-L77))),"") | X77: =IF(W77="","No Data",IF(W77>=1,"Achieved",IF(W77>=0.5,"On Track","Needs Attention"))) -> No Data | Y77: SSBB Project-Souptik Mondal
A78: 75 | B78: II | C78: 3927 | D78: Subhash Ghosh | E78: Unit-III | F78: Civil | G78: Vendor cost optimization | H78: Decreasing | V78: =IFERROR(AVERAGE(M78:S78),"") | W78: =IFERROR(IF(V78="","",IF(H78="Increasing",(V78-K78)/(L78-K78),(K78-V78)/(K78-L78))),"") | X78: =IF(W78="","No Data",IF(W78>=1,"Achieved",IF(W78>=0.5,"On Track","Needs Attention"))) -> No Data | Y78: SSBB Project-Subhash Ghosh
A79: 30 | B79: I | D79: Sugyan Dora | E79: Unit-IV | F79: DRI | G79: Improve the Avg Productivity of Kiln per day 3.83 ton/hr to 4 ton/hr for Kiln#1 | H79: Increasing | I79: MT/Hr | J79: Sep'25-Dec'25 | K79: 3.83 | L79: 4 | M79: 3.96 | N79: 3.96 | O79: 3.74 | P79: 3.76 | Q79: 3.83 | R79: 3.8 | S79: 3.83 | V79: =IFERROR(AVERAGE(M79:S79),"") -> 3.84 | W79: =IFERROR(IF(V79="","",IF(H79="Increasing",(V79-K79)/(L79-K79),(K79-V79)/(K79-L79))),"") -> 0.058823529 | X79: =IF(W79="","No Data",IF(W79>=1,"Achieved",IF(W79>=0.5,"On Track","Needs Attention"))) -> Needs Attention | Y79: SSBB Project-Sugyan Dora
A80: 31 | B80: I | D80: Sugyan Dora | E80: Unit-IV | F80: DRI | G80: Improve the Avg Productivity of Kiln per day 3.90 ton/hr to 4 ton/hr for Kiln#2 | H80: Increasing | I80: MT/Hr | J80: Sep'25-Dec'25 | K80: 3.9 | L80: 4 | M80: 3.9 | N80: 3.97 | O80: 3.88 | P80: 3.84 | Q80: 3.88 | R80: 3.89 | S80: 3.39 | V80: =IFERROR(AVERAGE(M80:S80),"") -> 3.8214286 | W80: =IFERROR(IF(V80="","",IF(H80="Increasing",(V80-K80)/(L80-K80),(K80-V80)/(K80-L80))),"") -> -0.78571429 | X80: =IF(W80="","No Data",IF(W80>=1,"Achieved",IF(W80>=0.5,"On Track","Needs Attention"))) -> Needs Attention | Y80: SSBB Project-Sugyan Dora
A81: 32 | B81: I | D81: Sugyan Dora | E81: Unit-IV | F81: DRI | G81: Improve the Avg Productivity of Kiln per day 3.76 ton/hr to 4 ton/hr for Kiln#3 | H81: Increasing | I81: MT/Hr | J81: Sep'25-Dec'25 | K81: 3.76 | L81: 4 | M81: 3.38 | N81: 3.86 | O81: 3.68 | P81: 2.95 | Q81: 4.09 | R81: 3.97 | S81: 3.84 | V81: =IFERROR(AVERAGE(M81:S81),"") -> 3.6814286 | W81: =IFERROR(IF(V81="","",IF(H81="Increasing",(V81-K81)/(L81-K81),(K81-V81)/(K81-L81))),"") -> -0.32738095 | X81: =IF(W81="","No Data",IF(W81>=1,"Achieved",IF(W81>=0.5,"On Track","Needs Attention"))) -> Needs Attention | Y81: SSBB Project-Sugyan Dora
A82: 33 | B82: I | D82: Sugyan Dora | E82: Unit-IV | F82: DRI | G82: Improve the Avg Productivity of Kiln per day 3.63 ton/hr to 4 ton/hr for Kiln#4 | H82: Increasing | I82: MT/Hr | J82: Sep'25-Dec'25 | K82: 3.63 | L82: 4 | M82: 3.65 | N82: 3.53 | O82: 3.89 | P82: 2.8 | Q82: 4.04 | R82: 4.07 | S82: 3.58 | V82: =IFERROR(AVERAGE(M82:S82),"") -> 3.6514286 | W82: =IFERROR(IF(V82="","",IF(H82="Increasing",(V82-K82)/(L82-K82),(K82-V82)/(K82-L82))),"") -> 0.057915058 | X82: =IF(W82="","No Data",IF(W82>=1,"Achieved",IF(W82>=0.5,"On Track","Needs Attention"))) -> Needs Attention | Y82: SSBB Project-Sugyan Dora
A83: 58 | B83: II | C83: 30103 | D83: Suman Majumder | E83: JSBIL | F83: Operation (Chemist) | G83: Reduce the Laboratory Operational cost per heat per day from 1392 to <1100. | H83: Decreasing | I83: INR/Heat | J83: Nov'25-Dec'25 | K83: 1392 | L83: 1100 | M83: 1348.3 | N83: 1148.71 | O83: 1159.25 | P83: 1085.74 | Q83: 1072.2 | R83: 1067.87 | S83: 1100 | T83: 1044.5 | V83: =IFERROR(AVERAGE(M83:S83),"") -> 1140.2957 | W83: =IFERROR(IF(V83="","",IF(H83="Increasing",(V83-K83)/(L83-K83),(K83-V83)/(K83-L83))),"") -> 0.86200098 | X83: =IF(W83="","No Data",IF(W83>=1,"Achieved",IF(W83>=0.5,"On Track","Needs Attention"))) -> On Track | Y83: SSBB Project-Suman Majumder
A84: 42 | B84: II | C84: 3413 | D84: Surajit Thakur | E84: Unit-III | F84: Electrical | G84: Reduce Power Consumption per Heat of Furnace-2 from 6951 kWh to <6700 kWh in LCFC Plant. | H84: Decreasing | I84: kWh/Heat | J84: Oct'25-Dec'25 | K84: 6951 | L84: 6700 | M84: 6845 | N84: 6963 | O84: 6703 | P84: 6664 | Q84: 6647 | R84: 6635 | V84: =IFERROR(AVERAGE(M84:S84),"") -> 6742.8333 | W84: =IFERROR(IF(V84="","",IF(H84="Increasing",(V84-K84)/(L84-K84),(K84-V84)/(K84-L84))),"") -> 0.82934927 | X84: =IF(W84="","No Data",IF(W84>=1,"Achieved",IF(W84>=0.5,"On Track","Needs Attention"))) -> On Track | Y84: SSBB Project-Surajit Thakur
A86: Legend: | B86: Achieved | C86: On Track | D86: Needs Attention
A87: Note: 'Average (Actual)' = mean of Jan-Jun actuals entered. 'Progress %' compares Average vs Target relative to Baseline, direction-aware (Increasing/Decreasing). Source: Master Data sheet, 15projects_SSBB_Final.xlsx (Jan–Jun 2026 tracking).

Sheet Sheet2
A7: B | B7: Product
A8: B1 | B8: Mould
A9: B11 | B9: industrial sectior
A10: B11.1 | B10: DI pipe industries
B11: Sizes (mm) | C11: DN 100 to 350
B12: Length(mm) | C12: 5.5
A13: B2 | B13: Ring Forging
A14: B2.1 | B14: industrial sectior
B15: Wind energy
B16: Heavy Machinaries

Sheet Maintenance
A2: P | B2: Maintain A Machine
A3: P1 | B3: Select Machine
A4: P2 | B4: Install & commision the Machine
A5: P3 | B5: Use the Machine
A6: P4 | B6: Maintain the Machine
A7: P5 | B7: Assess the Helth of the Machine
A8: P6 | B8: Modify the machine

Sheet DCP-Conpilation 
A3: T2 | B3: T1 | C3: C1 | D3: X1 | E3: Y | F3: Z1 | G3: Z2 | H3: Z3 | I3: Z3.1
A4: Month | B4: Date | C4: Day | D4: Volume of Product | E4: % Absentism | F4: inventory volume | G4: Rejection | H4: Financial | I4: Over time

Sheet Sheet3

Sheet DCP-Collection
A2: T1 | B2: T2 | C2: T3 | D2: C1 | E2: X21 | F2: X22 | G2: X3 | H2: I1 | I2: I1' | J2: I2 | K2: X1 | L2: U1 | M2: Y-Micro | N2: Y | O2: Z1 | P2: Z2 | Q2: Z3 | R2: Z3.1
A3: Month | B3: Date | C3: Shift | D3: Day | E3: No of Labourer | G3: Labours | H3: Role No | I3: Name | J3: Gender | K3: Volume of Product(MT) | L3: Cause for Absentism | M3: Absent-1 Present-0 | N3: % Absentism | O3: inventory volume | P3: Rejection | Q3: Financial | R3: Over time
E4: Plan | F4: Actual
A5: 46235 | B5: 2
C6: A | D6: Mon | E6: 120 | F6: 100 | K6: 125 | N6: =(E6-F6)/E6 -> 0.16666667
G7: L1 | M7: 0
M8: 0
M9: 1
M10: 0
M11: 0
M12: 0
A13: 46235 | B13: 2 | C13: B | D13: Mon

Sheet Quality-DCP
A1: Supplier | B1: R&D
A2: Input | B2: Requiremnts of mining
A3: Code | B3: P | C3: P1 | D3: P2 | E3: P3 | F3: P4 | G3: P5 | H3: P6
A4: Process | B4: Mining Mgmt | C4: Identify the sources | D4: select the source | E4: Communicate the requirement of vendor of the source | F4: Materialized or crytalized | G4: Generic /Special/ requirement
A5: Resource | B5: Lab
A6: Output | B6: Test Result
A7: Customer | B7: Pdn / Comm / Mgmt
A9: CODE | B9: T1 | C9: I1 | D9: C1 | E9: C2 | F9: C3 | G9: C4 | H9: X1 | I9: Y1 | J9: Y11 | K9: Y12 | L9: Y13 | M9: Y14 | N9: Y15 | O9: Y16 | P9: Y17 | Q9: Y18 | R9: Y2 | S9: Y21 | T9: Y22 | U9: Y23 | V9: Y24 | W9: U1
A10: CTQ --> | B10: Date | C10: Iron ores | D10: Batch | E10: Mines | F10: Sampler | G10: Type of Product | H10: Sample Qty | I10: Chemical properties | J10: T-Fe | K10: SiO2 | L10: Al2O3 | M10: P | N10: Mn | O10: TiO2 | P10: Cr | Q10: Zn | R10: Physical properties | S10: Moisture | T10: Oversize | U10: Undersize | V10: Tumbler Index | W10: Remark
A11: DCP
A12: Description
A13: Type of Data
A14: UOM
A15: Type of Spec
A16: USL
A17: TARGET
A18: LSL
A19: Minimum Frequency of Data
A20: Data Source
A21: Resposibility
A22: Reaction Plan or Troubleshooting checklist
... A38: Comment on Accuracy

Sheet DFSS
A2: 1 | B2: Inroducing DFSS
A3: 1.01 | B3: New product
A4: 1.02 | B4: New service
A5: 1.03 | B5: New process
A6: 1.03.01 | B6: Manufacturing process
A7: 1.03.02 | B7: Service provision
A8: 1.04 | B8: New system
A9: 1.05 | B9: New Software
A10: 1.06 | B10: New competency
A11: 2 | B11: MGAP for company
A12: 2.01 | B12: MGMT(Multigeneration market trends)
A13: 2.02 | B13: MGPP(Multigeneration product Plan)
A14: 2.03 | B14: MGPP(Multigeneration Process Plan)
A15: 2.04 | B15: MGTP(Multigeneration Technology platform
A16: 2.04.01 | B16: Product Technology
A17: 2.04.02 | B17: Process Technology
A18: 2.05 | B18: Critical Assumptions
A19: 3 | B19: Type of New
A20: 3.01 | B20: New to the world
A21: 3.02 | B21: New to the Company
A22: 3.03 | B22: New to the product family
A23: 3.04 | B23: New to the product line
A24: 3.05 | B24: New to the Brand of the same product line for the same product family
A25: 3.06 | B25: Same product with more alternative application
A26: 3.07 | B26: Same product with reduced cost
A27: 3.08 | B27: New product with small-small added features
A28: 4 | B28: DFSS issue hopper
A29: 5 | B29: Define phase of DFSS
A30: 6 | B30: Project charter
A31: 7 | B31: Surrogate Selection | C31: For Surrogate | E31: Representative person or premises | F31: Additional expectation of new product | G31: Risk | H31: Requirement
A32: 8 | B32: Product life cycle member identification | C32: Strength | D32: weakness
A33: 8.01 | B33: TLC (Technology life cycle) Members
A34: 8.01.01 | B34: Induction Hardening
A35: 8.01.02
A36: 8.01.03
A37: 8.01.04
A38: 8.02 | B38: DLC (Design life Cycle ) Members
A39: 8.02.01
A40: 8.02.02
A41: 8.02.03
A42: 8.03 | B42: In Bound Supply chain-Sourcing , input ,requirement or concerns
A43: 8.04 | B43: Manufacturer -Received of Raw material to storage of Finished goods
A44: 8.05 | B44: Manufacturer to Customer-out bound supply chain-logistics
A45: 8.05.01 | B45: Finished goods stores
A46: 8.05.02 | B46: Packaging
A47: 8.05.02.01 | B47: Primary
A48: 8.05.02.02 | B48: Secondary
A49: 8.05.02.03 | B49: Tertiary
A50: 8.05.02.04 | B50: Cargo
A51: 8.05.02.05 | B51: Loading
A52: 8.05.02.06 | B52: Unloading
A53: 8.05.03 | B53: Transport
A54: 8.05.03.01 | B54: Surface
A55: 8.05.03.01.01 | B55: Truck
A56: 8.05.03.01.02 | B56: Freight insurance
... A72: 8.05.07 | B72: Governments Law for out bound
A73: 8.06 | B73: Product in field with customers | C73: Representative person | E73: E-mail address | F73: Mob. No | G73: Concern | H73: Requirement
A74: 8.06.01 | B74: Product used environment
A75: 8.06.02 | B75: who take the decision to purchase the product from customer family
A76: 8.06.03 | B76: A member of a Customer family to take a decision how the product deliver to customer facility
A77: 8.06.04 | B77: Who used the product
A78: 8.06.05 | B78: How to product to be Maintain
A79: 8.06.06 | B79: spare part for maintain
A80: 8.06.07 | B80: Servicing
A81: 8.07 | B81: Disposition of product against Suffocation & Proposition of Customer & Government Condition
A82: 8.07.01 | B82: Customer
A83: 8.07.01.01 | B83: Resale value
A84: 8.07.01.02 | B84: Re-cycle
A85: 8.07.02 | B85: Government
A86: 8.07.02.01 | B86: Legality of disposition
A88: 9 | B88: VoS & Risk mitigation plan
A89: 10 | B89: ER Layer
A90: 11 | B90: E -CTQ Dashboard
A91: 12
A92: 13
A93: 14
A94: 15
A95: 16
A96: 1 | B96: Marketing
A97: 2 | B97: sales
A98: 3 | B98: Orders
A99: 4 | B99: R&D if Required
A100: 5 | B100: Expand capacity
A101: 6 | B101: Product design
A102: 7 | B102: Planning
A103: 7.01 | B103: Plan for RM (In bound supply chain)
A104: 7.01 | B104: Man power
A105: 7.01 | B105: Machine
A106: 7.01 | B106: Utility
A107: 7.01 | B107: Method
... A119: 13.01 | B119: Specific Support services
A120: 13.01.01 | B120: RM, Manpower, Machine,Method, Utility
A121: 13.02 | B121: Generic support Services-
A122: 13.02.01 | B122: Corporate
A123: 13.02.02 | B123: HR
A124: 13.02.03 | B124: Information Management system
A125: 13.02.04 | B125: Finance
A126: 13.02.05 | B126: Account
A127: 13.02.06 | B127: SHE& F
A128: 13.02.07 | B128: legal
...

Sheet MGPP
AH1: short term | AJ1: Mid term | AK1: Long term
AG2: Current year | AH2: ABP | AJ2: SBP | AK2: MGP
E3: 1998-99 | F3: 1999-2000 | G3: 2000-2001 | H3: 2001-2002 | I3: 2002-2003 | J3: 2003-2004 | K3: 2004-2005 | L3: 2005-06 | M3: 2006-07 | N3: 2007-08 | O3: 2008-09 | P3: 2009-10 | Q3: 2010-11 | R3: 2011-12 | S3: 2012-13 | T3: 2013-14 | U3: 2014-15 | V3: 2015-16 | W3: 2016-17 | X3: 2017-18 | Y3: 2018-19 | Z3: 2019-20 | AA3: 2020-21 | AB3: 2021-22 | AC3: 2022-23 | AD3: 2023-24 | AE3: 2024-25 | AF3: 2025-26 | AG3: 2026-27 | AH3: 2027-28 | AI3: 2028-29 | AJ3: 2029-30 | AK3: 2030-31 | AL3: 2031-32 | AM3: 2032-33 | AN3: 2033-34 | AO3: 2034-35 | AP3: 2035-36 | AQ3: 2036-37 | AR3: 2037-38 | AS3: 2038-39 | AT3: 2039-40
A5: A | B5: Product | D5: UOM
A6: M | B6: Market
A7: M01 | B7: No of Customers
A8: M02 | B8: Market share (%)
A9: M03 | B9: No of Competitors
A10: M03.01 | B10: Competitor-1
A11: M03.02 | B11: Competitor-2
A12: M03.03 | B12: Competitor-3
A13: M03.04 | B13: Competitor-4
A14: M04 | B14: Avg Revenue Per unit of Customer per year
A15: M05 | B15: Revenue
A16: M06 | B16: Investment
A17: M07 | B17: Profits
... A20: A01 | B20: DIP
A21: A01.01 | B21: DI pipe | C21: Volume | D21: MT
C22: Value | D22: Cr.
A23: A01.02 | B23: PIG iron | C23: Volume | D23: MT
C24: Value | D24: Cr.
A25: A02 | B25: Ferro Alloys
A26: A02.01 | B26: LCFC | C26: Volume | D26: MT
C27: Value | D27: Cr.
A28: A02.02 | B28: MCFC | C28: Volume | D28: MT
C29: Value | D29: Cr.
A30: A04 | B30: TMT Bar | C30: Volume | D30: MT
C31: Value | D31: Cr.
A32: A05 | B32: DRI | C32: Volume | D32: MT
C33: Value | D33: Cr.
B34: Billets | C34: Volume | D34: MT
C35: Value | D35: Cr.
B36: Nail | C36: Volume | D36: MT
C37: Value | D37: Cr.
B38: Coke | C38: Volume | D38: MT
C39: Value | D39: Cr.
B40: MS rod | C40: Volume | D40: MT
C41: Value | D41: Cr.
B42: OPVC | C42: `
B44: By Product
B46: G- slag
B48: Hopper slag
B50: Runner scrap
B52: Rejection pipe
A53: B | B53: Process
A54: B01 | B54: Unit-I | C54: Capacity
C55: Volume
A56: B02 | B56: Unit-II | C56: Capacity
C57: Volume
A58: B03 | B58: Unit-III | C58: Capacity
C59: Volume
A60: B04 | B60: Unit-IV | C60: Capacity
C61: Volume
A62: B05 | B62: Unit-V | C62: Capacity
C63: Volume
A64: C | B64: Technology Platform
A65: C01 | B65: Product Technology
A66: C02 | B66: Process Technology
A67: D | B67: Critical Assumption
B69: New-Double chamber Restraint Joint
B70: Surrogate product
B71: Single chamber Restraint joint
B72: Socket spigot Push on joint

Sheet MGAP
K3: Short term | O3: Mid term | Q3: Long term
E4: 2024-25 | G4: 2025-26 | I4: 2026-27 | K4: 2027-28 | M4: 2028-29 | O4: 2029-30 | Q4: 2030-35 | S4: 2035-40 | U4: 2040-50
I5: Current year | K5: ABP (Annual Business plan) | O5: SBP(strategic Business plan) | Q5: MGP(Multigenration plan)
D6: UOM | E6: Actual | F6: Plan | G6: Actual | H6: Plan | I6: Actual | J6: Plan | K6: Actual | L6: Plan | M6: Actual | N6: Plan | O6: Actual | P6: Plan | Q6: Actual | R6: Plan | S6: Actual | T6: Plan | U6: Actual | V6: Plan
A7: A | B7: Market
A8: A.01 | B8: Customer
A9: A.01.01 | B9: No of Customer
A10: A.01.02 | B10: ARPU(Avg Revenue of per unit of per Customers per year
A11: A.02 | B11: Finance
A12: A.02.01 | B12: Revenue
A13: A.02.02 | B13: Expenditure
A14: A.02.03 | B14: Tax
A15: A.03 | B15: Competitors
A16: A.03.01 | B16: No of Competitors
A17: A.03.01A | B17: Competitor 1------
A18: A.03.02 | B18: Market share of all competitors
... A32: B | B32: Product
A33: B1 | B33: DI pipe | C33: Volume | D33: MT | E33: 400000 | F33: 500000 | G33: 150000 | H33: 200000 | I33: 200000 | J33: 300000 | L33: 550000 | N33: 550000
C34: value | D34: cr | E34: =E33*50000/10^7 -> 2000 | F34: =F33*50000/10^7 -> 2500 | G34: =G33*50000/10^7 -> 750 | H34: =H33*50000/10^7 -> 1000 | I34: =I33*50000/10^7 -> 1000 | J34: =J33*50000/10^7 -> 1500 | L34: =L33*50000/10^7 -> 2750 | N34: =N33*50000/10^7 -> 2750
A35: B1.01
A36: B1.02
A37: B1.03
A38: B1.04
A39: B1.05
A40: B1.06
A41: B1.07
A42: B1.08
A43: B1.09
A44: B1.10
A45: B1.11
A46: B1.12
... A51: B1.17
A52: B2 | B52: PIG iron | C52: Volume
C53: value
A54: B3 | B54: LCFC | C54: Volume
C55: value
A56: B4 | B56: By product | C56: Volume
C57: value
A66: B4.01 | B66: Runner Scrap | C66: Volume
C67: value
A68: B4.02 | B68: DI Slag | C68: Volume
C69: value
A70: B4.03 | B70: Rejected pipe | C70: Volume
C71: value
A72: B4.04 | B72: Granulated slag | C72: Volume
C73: value
A74: B4.05 | B74: Slag bolder | C74: Volume
C75: value
A76: B4.06 | B76: Runner dust | C76: Volume
C77: value
A78: B4.07 | B78: Core sand | C78: Volume
C79: value
A80: B4.08 | B80: Zn Cut wire & dust | C80: Volume
C81: value
A82: B4.09 | B82: Cutting DI pipe dust | C82: Volume
C83: value
A84: B4.10 | B84: BF Gas | C84: Volume
C85: value
A86: C | B86: Process
A87: C.01 | B87: Unit-III
A88: C.01-01 | B88: Capacity
A89: C.01-02
A90: C.02
A91: C.03

Sheet Sheet1
A1: SIX SIGMA / SSBB PROJECT TRACKING SHEET
A2: Participants | Project Theme | Baseline Period, UOM & Data | Target | Monthly Tracking (Jan–Jun) | Location & Department
A4: PROJECT & PARTICIPANT INFO | H4: PROJECT TYPE | K4: BASELINE & TARGET | M4: MONTH-WISE ACTUAL TRACKING (JAN – JUN) | S4: PERFORMANCE SUMMARY
A5: S.No | B5: Batch | C5: Employee Code | D5: Participant's Name | E5: Location / Unit | F5: Department | G5: Project Theme / Title | H5: Improvement Direction | I5: Baseline UOM | J5: Baseline Period | K5: Baseline Data | L5: Target | M5: Jan-26 | N5: Feb-26 | O5: Mar-26 | P5: Apr-26 | Q5: May-26 | R5: Jun-26 | S5: Average (Actual) | T5: Progress % | U5: Status
A6: 5 | B6: I | D6: Sandip Sil ,A.P Sahoo,Sudipta Chatterjee,Ashish Ranjan | E6: Unit-III | F6: DIP Operation | G6: Reducing over all rejection of DIP from 9.8 to 6.8 % for K9. | H6: Decreasing | I6: % | J6: Dec'24-Oct'25 | K6: 9.8 | L6: 6.8 | M6: 4.41 | N6: 4.02 | O6: 5.98 | P6: 5.49 | Q6: 7.28 | R6: 4.21 | S6: 5.2316667 | T6: 1.5227778 | U6: Achieved
A7: 7 | D7: Sandipan Ghosh | E7: Unit-III | F7: RMHS Electrical | G7: Increase the average plant availability of Iron Ore Washery from 81.70% per day to >90% for IOW-2. | H7: Increasing | I7: % | J7: Apr'25-Oct'25 | K7: 81.77 | L7: 90 | M7: 96.3 | N7: 95.264583 | O7: 96.3 | P7: 95.630769 | Q7: 95.37 | R7: 96.15 | S7: 95.835892 | T7: 1.7090999 | U7: Achieved
A8: 12 | B8: II | C8: 7448 | D8: Prasanta Karmakar | E8: Unit-III | F8: RMHS Operation | G8: Increase the average monthly efficiency of Iron ore Washery Plant-1 from 77.25 % to >85%. | H8: Increasing | I8: % | J8: Apr'25-Sept-25 | K8: 77.25 | L8: 85 | M8: 95.1 | N8: 92.24 | O8: 87.6 | P8: 86.11 | Q8: 96.05 | R8: 90.87 | S8: 91.328333 | T8: 1.8165591 | U8: Achieved
A9: 13 | B9: II | C9: 7448 | D9: Prasanta Karmakar | E9: Unit-III | F9: RMHS Operation | G9: Increase the average monthly efficiency of Iron ore Washery Plant-2 from 78.26 % to >85% | H9: Increasing | I9: % | J9: Apr'25-Sept-25 | K9: 78.26 | L9: 85 | M9: 91.61 | N9: 94.07 | O9: 95.7 | P9: 95.96 | Q9: 96.46 | R9: 97.61 | S9: 95.235 | T9: 2.518546 | U9: Achieved
A10: 25 | B10: II | C10: 4382 | D10: Prithwis Bhattacharya | E10: Unit-III | F10: DIP Mechanical | G10: To reduce the frequency of downtime per month in M/C 5 from 58 to 46 respectively i.e increase MTBF without increase MTTR. | H10: Decresing | I10: Nos. | J10: Nov'24-Oct'25 | K10: 56 | L10: 46 | M10: 32 | N10: 14 | O10: 45 | Q10: 80 | R10: 50 | S10: 44.2 | T10: 1.18 | U10: Achieved
A11: 26 | B11: II | C11: 4382 | D11: Prithwis Bhattacharya | E11: Unit-III | F11: DIP Mechanical | G11: To reduce the frequency of downtime per month in M/C 6 from 55 to 44 respectively i.e increase MTBF without increase MTTR. | H11: Decresing | I11: Nos. | J11: Nov'24-Oct'25 | K11: 54 | L11: 44 | M11: 44 | N11: 34 | O11: 36 | P11: 33 | Q11: 47 | R11: 55 | S11: 41.5 | T11: 1.25 | U11: Achieved
A12: 28 | B12: II | C12: 4382 | D12: Prithwis Bhattacharya | E12: Unit-III | F12: DIP Mechanical | G12: To reduce the frequency of downtime per month in M/C 9 from 63 to 50 respectively i.e increase MTBF without increase MTTR. | H12: Decresing | I12: Nos. | J12: Nov'24-Oct'25 | K12: 74 | L12: 50 | M12: 21 | N12: 28 | O12: 55 | P12: 19 | Q12: 57 | R12: 50 | S12: 38.333333 | T12: 1.4861111 | U12: Achieved
A13: 36 | B13: I | C13: 45833 | D13: Papan Nayak | E13: Unit-IV | F13: CPP Operations | G13: Reduce the Avg Steam loss of Power Plant per month from 8895 to 2261 ton. | H13: Increasing | I13: Ton/Month | J13: Dec'24-Oct25 | K13: 8894 | L13: 2261 | M13: 859 | N13: 528 | O13: 550 | P13: 371 | Q13: 390 | R13: 586 | S13: 547.33333 | T13: 1.2583547 | U13: Achieved
A14: 42 | B14: II | C14: 2483 | D14: B.K Mishra | E14: Unit-III | F14: Coke Oven Operation | G14: Reduce the Ash % in Coke of Coke oven plant per month from 12.84 to <12.5 . | H14: Decresing | I14: % | J14: Jul'25-Dec'25 | K14: 12.92 | L14: 12.5 | M14: 12.1 | N14: 12.42 | O14: 12.74 | P14: 12.44 | Q14: 12.56 | R14: 12.01 | S14: 12.378333 | T14: 1.2896825 | U14: Achieved
A15: 45 | B15: II | C15: 6095 | D15: Biswanath Banerjee | E15: Unit-III | F15: Drawings and Design | G15: Reduce the Invisible Zn losses of DIP per day from 41.03 gram/m2 to 12.0gram/m2 . | H15: Decresing | I15: Gram/m2 | J15: Jul'25-Oct'25 | K15: 41.13 | L15: 12 | M15: 11.35 | N15: 11.59 | O15: 9.8 | P15: 13.36 | Q15: 14.36 | R15: 10.49 | S15: 11.825 | T15: 1.0060076 | U15: Achieved
A16: 46 | B16: I | C16: 6323 | D16: Nagesh Kumar | E16: Unit-III | F16: DIP Electrical | G16: Reduce the specific power consumption of DIP Compressor from 52.83 KWH/MT to 35 KWH/MT per day. | H16: Decresing | I16: Kwh/MT | J16: Augt'25-Nov'25 | K16: 38.75 | L16: 35 | M16: 20 | N16: 23 | O16: 24 | P16: 29 | Q16: 28 | R16: 25 | S16: 24.833333 | T16: 3.7111111 | U16: Achieved
A17: 49 | B17: I | C17: 48356 | D17: Gourav Sarkar | E17: Unit-IV | F17: BE -RM Operation | G17: Reduce Average Specific Power Consumption of Induction Heater Per Day from 41 to 25. | H17: Decresing | I17: Kwh/MT | J17: Sep'25-Dec'25 | K17: 34 | L17: 25 | M17: 22 | N17: 22 | O17: 22 | P17: 20 | Q17: 21 | R17: 22 | S17: 21.5 | T17: 1.3888889 | U17: Achieved
A18: 51 | B18: II | C18: 8216 | D18: Pankaj Dubey | E18: Unit-III | F18: Human Resource | G18: Reducing LWP per month from 3.094 to <2%. | H18: Decresing | I18: % | J18: Jan'25-Sep'25 | K18: 3.1 | L18: 2 | M18: 0.93194136 | N18: 1.4 | O18: 1.7 | P18: 2.1 | Q18: 2.2 | R18: 2.1 | S18: 1.7386569 | T18: 1.2375846 | U18: Achieved
A19: 63 | B19: II | C19: 50618 | D19: Sohel Rana | E19: Unit-IV | F19: Business Excellence | G19: Breakdown reduction in rolling Mill #2 from 15.03 % to <10.0% | H19: Decresing | I19: % | J19: Oct'25-Dec'25 | K19: 15.03 | L19: 10 | M19: 8.14 | N19: 6.3 | O19: 6.8 | P19: 5.5 | Q19: 11.18 | R19: 7.63 | S19: 7.5916667 | T19: 1.4787939 | U19: Achieved
A20: 17 | B20: II | C20: 48956 | D20: Sailesh Singh Yadav | E20: Unit-IV | F20: Operation | G20: Cr Recovery from 87 % to > 90%( Grade - Cr-66 & C-0.75 %) in Ferro alloys division in AOD | H20: Increasing | I20: % | J20: Oct'25-Dec'25 | K20: 86.53 | L20: 90 | M20: 87.19 | N20: 90.3 | O20: 90.17 | Q20: 90.89 | S20: 89.6375 | T20: 0.89553314 | U20: On Track
A21: 19 | B21: I | C21: 49269 | D21: Sanjay Nayak | E21: Unit-IV | F21: Ferro Operations | G21: Average the Cr recovery of Furnace -2 80.23 % per month 85.0 % per Month | H21: Increasing | I21: % | J21: Sept'25 - Dec'25 | K21: 80.23 | L21: 85 | M21: 76.27 | N21: 84.1 | O21: 79.73 | P21: 83.02 | Q21: 82.88 | R21: 90.060667 | S21: 82.676778 | T21: 0.51295132 | U21: On Track
A22: 21 | B22: II | C22: 7313 | D22: Pushpendra Ganguly | E22: Unit-III | F22: MBF Operation | G22: Increase the Avg Productivity of MBF2 per day from 3.01 Ton/m3 to >3.606 Ton/m3 . | H22: Increasing | I22: Ton/day/m3 | J22: Jul'25-Oct'25 | K22: 3.01 | L22: 3.6 | M22: 3.31 | N22: 3.25 | O22: 3.41 | P22: 3.47 | Q22: 3.38 | R22: 3.5 | S22: 3.3866667 | T22: 0.63841808 | U22: On Track
A23: 27 | B23: II | C23: 4382 | D23: Prithwis Bhattacharya | E23: Unit-III | F23: DIP Mechanical | G23: To reduce the frequency of downtime per month in M/C 7A from 75 to 60 respectively i.e increase MTBF without increase MTTR. | H23: Decresing | I23: Nos. | J23: Nov'24-Oct'25 | K23: 81 | L23: 60 | M23: 62 | N23: 50 | O23: 65 | P23: 89 | Q23: 91 | R23: 34 | S23: 65.166667 | T23: 0.75396825 | U23: On Track
A24: 30 | B24: I | D24: Shantimoy Som | E24: Unit-III | F24: Coke Oven | G24: Increase Avg steam of WHRB plant from 44958 Ton/Month to 53949 Ton/Month . | H24: Increasing | I24: MT/Month | J24: Oct24-Sep'25 | K24: 44958 | L24: 53949 | M24: 59458 | N24: 49434 | O24: 41040 | P24: 52788 | Q24: 58582 | R24: 54972 | S24: 52712.333 | T24: 0.86245505 | U24: On Track
A25: 43 | B25: I | C25: 49096 | D25: Goutam Patel | E25: Unit-IV | F25: Business Excellence | G25: Reduce the specific power Consumption of Furnace-2 per day from 4251 kWh/MT to 3700 kWh/MT of Ferro Alloys. | H25: Decresing | I25: Kwh/MT | J25: April-25 -Jan'26 | K25: 4251 | L25: 3700 | N25: 3775.8362 | O25: 4010.5588 | P25: 3850.386 | Q25: 3920.7315 | R25: 3837.6282 | S25: 3879.0281 | T25: 0.67508506 | U25: On Track
A26: 44 | B26: II | C26: 3413 | D26: Surajit Thakur | E26: Unit-III | F26: Electrical | G26: Reduce Power Consumption per Heat of Furnace-2 from 6951 kWh to <6700 kWh in LCFC Plant. | H26: Decresing | I26: kWh/Heat | J26: Oct'25-Dec'25 | K26: 6951 | L26: 6700 | M26: 6845 | N26: 6963 | O26: 6703 | P26: 6664 | Q26: 6647 | R26: 6635 | S26: 6742.8333 | T26: 0.82934927 | U26: On Track
A27: 47 | B27: I | C27: 10952 | D27: Prakash Joshi | E27: Unit-III | F27: Human Resource | G27: Manpower cost optimization per month from 7.04 cr to 6.8 cr of Unit-III. | H27: Decresing | I27: Crore | J27: June-25-Sept'25 | K27: 7.04 | L27: 6.8 | M27: 6.41 | N27: 6.7 | O27: 6.98 | P27: 7.12 | Q27: 7.1 | S27: 6.862 | T27: 0.74166667 | U27: On Track
A28: 50 | B28: II | C28: 5612 | D28: Manoj Kumar | E28: Unit-III | F28: Safety | G28: Reducing Mandays loss of Jai Balaji Unit-3 from 1546 per month to 600 per /month | H28: Decresing | I28: Days | J28: Jun'24-Dec'25 | K28: 1591 | L28: 600 | M28: 1637 | N28: 1108 | O28: 77 | P28: 84 | S28: 726.5 | T28: 0.87235116 | U28: On Track
A29: 1 | B29: I | C29: 16923 | D29: Akram Imran | E29: Unit-I | F29: Operations | G29: Improve the Avg Productivity of Kiln per Month from 37.42 ton to 43 ton for Kiln#1 | H29: Increasing | I29: TPD | J29: Dec'24 -Sept'25 | K29: 37.42 | L29: 43 | M29: 28.76 | N29: 42.01 | O29: 30.72 | P29: 42.75 | Q29: 39.423077 | R29: 42.666667 | S29: 37.721624 | T29: 0.054054468 | U29: Needs Attention
A30: 2 | B30: I | C30: 16407 | D30: Manas Mukherjee | E30: Unit-I | F30: Ferro Operations | G30: Increase the Avg Metal recovery(High SiMg) from 83.48% to 90 % for Furnace #1 | H30: Increasing | I30: % | J30: Jan'25-Sept25 | K30: 83.48 | L30: 90 | M30: 84.26 | N30: 82.75 | S30: 83.505 | T30: 0.0038343558 | U30: Needs Attention
A31: 3 | B31: I | C31: 4 | D31: Ravindra Kumar Meherwal | E31: Unit-III | F31: Central Electrical | G31: Increase the Avg Load factor of LCFC per month(for furnace 1 to 5) from 0.78 to 0.83. | H31: Increasing | I31: Load Factor | J31: Jul'25-Oct'25 | K31: 0.78 | L31: 0.83 | M31: 0.79 | N31: 0.73 | O31: 0.80298469 | P31: 0.77706842 | Q31: 0.79189895 | R31: 0.73794202 | S31: 0.77164901 | T31: -0.16701974 | U31: Needs Attention
A32: 4 | B32: I | C32: 10818 | D32: Sandip Sil ,A.P Sahoo,Sudipta Chatterjee,Ashish Ranjan | E32: Unit-III | F32: DIP Operation | G32: Reducing over all rejection of DIP from 12.7 % to 9.7 % .for K7 . | H32: Decreasing | I32: % | J32: Dec'24-Oct'25 | K32: 12.7 | L32: 9.7 | M32: 9.65 | N32: 9.64 | O32: 10.26 | P32: 13.26 | Q32: 13.84 | R32: 12.47 | S32: 11.52 | T32: 0.39333333 | U32: Needs Attention
A33: 6 | B33: I | C33: 4939 | D33: Sandipan Ghosh | E33: Unit-III | F33: RMHS Electrical | G33: Increase the average plant availability of Iron Ore Washery from 84.48 % per day to >90% for IOW-1 . | H33: Increasing | I33: % | J33: Apr'25-Oct'25 | K33: 84.48 | L33: 90 | M33: 97.037037 | N33: 81.458333 | O33: 73.888889 | P33: 86.923077 | Q33: 86.555556 | R33: 93.32 | S33: 86.530482 | T33: 0.37146412 | U33: Needs Attention
A34: 8 | B34: I | C34: 464 | D34: Binoy Kumar Vishwakarma | E34: Unit-III | F34: Sinter Operation | G34: Reduce the specific energy consumption per ton of sinter from 299887 to <284652 Kcal/TS. | H34: Decreasing | I34: % | J34: Jan'25-Dec'25 | K34: 299634 | L34: 284652 | M34: 308018.8 | N34: 384278.8 | O34: 345679.5 | P34: 309111.7 | Q34: 266104 | R34: 255905.3 | S34: 311516.35 | T34: -0.7931084 | U34: Needs Attention
A35: 9 | B35: II | C35: 6363 | D35: Molay Pan | E35: Unit-III | F35: Coke Oven Electrical | G35: Reduce Specific energy consumption per day of Coke oven plant from 9.36 KWh/Ton to < 8 KWh/Ton . | H35: Decreasing | I35: KWh/Ton | J35: Jan'25 - Dec'25 | K35: 9.36 | L35: 8 | M35: 7.99 | N35: 8.38 | O35: 8.88 | P35: 9.46 | Q35: 9.6 | R35: 11.14 | S35: 9.2416667 | T35: 0.087009804 | U35: Needs Attention
A36: 10 | B36: II | C36: 7855 | D36: Harsh Sharma | E36: Unit-III | F36: Sinter Mechanical | G36: Reducing Down time per month from 8.77 to < 5 hr for SP1 . | H36: Decreasing | I36: Hrs/month | J36: May'25-Aug'25 | K36: 8.77 | L36: 5 | M36: 7.11 | N36: 5.5 | O36: 6.66 | P36: 11.25 | Q36: 8.08 | R36: 6.08 | S36: 7.4466667 | T36: 0.3510168 | U36: Needs Attention
A37: 11 | B37: II | C37: 7855 | D37: Harsh Sharma | E37: Unit-III | F37: Sinter Mechanical | G37: Reducing Down time per month from from 6.13 to < 3 hr for SP2. | H37: Decresing | I37: Hrs/month | J37: May'25-Aug'25 | K37: 6.13 | L37: 3 | M37: 13.5 | N37: 5.2 | O37: 4.58 | P37: 4.83 | Q37: 3.25 | R37: 5.16 | S37: 6.0866667 | T37: 0.013844515 | U37: Needs Attention
A38: 16 | B38: II | C38: 48956 | D38: Sailesh Singh Yadav | E38: Unit-IV | F38: Operation | G38: Cr Recovery from 87 % to > 90% ( Grade - Cr-60 & C-5 %) in Ferro alloys division in AOD | H38: Increasing | I38: % | J38: Augt'25-Dec'25 | K38: 88.79 | L38: 90 | N38: 86.16 | O38: 84.35 | R38: 83.39 | S38: 84.633333 | T38: -3.4352617 | U38: Needs Attention
A39: 18 | B39: I | C39: 49269 | D39: Sanjay Nayak | E39: Unit-IV | F39: Ferro Operations | G39: Average the Cr recovery of Furnace -1 84.93 % per month 88.0 % per Month | H39: Increasing | I39: % | J39: Sept'25 - Dec'25 | K39: 84.93 | L39: 88 | M39: 85.3 | N39: 86.08 | O39: 84.1 | P39: 81.44 | Q39: 84.68 | R39: 85.038333 | S39: 84.439722 | T39: -0.1596996 | U39: Needs Attention
A40: 20 | B40: I | C40: 49269 | D40: Sanjay Nayak | E40: Unit-IV | F40: Ferro Operations | G40: Average the Cr recovery of Furnace -III 87.83 % per month 90.0 % per Month | H40: Increasing | I40: % | J40: Sept'25 - Dec'25 | K40: 87.83 | L40: 90 | M40: 87.7 | N40: 87.18 | O40: 84.24 | P40: 83.85 | Q40: 86.15 | R40: 74.461667 | S40: 83.930278 | T40: -1.797107 | U40: Needs Attention
A41: 22 | B41: I | C41: 0 | D41: Samanway Das | E41: Unit-III | F41: MBF Operation | G41: Reduce the Fuel consumption of Blast furnace 2 per day from 607 Kg/THM to 550 Kg/THM. | H41: Decresing | I41: Kg/THM | J41: Jul'25-Oct'25 | K41: 628 | L41: 550 | M41: 627 | N41: 629 | O41: 615 | P41: 597 | Q41: 610 | R41: 592 | S41: 611.66667 | T41: 0.20940171 | U41: Needs Attention
A42: 23 | B42: I | D42: Samanway Das | E42: Unit-III | F42: MBF Operation | G42: Reduce coke Rate of Blast furnace 2 per day from ---- Kg/THM to ---- Kg/THM. | H42: Decresing | I42: Kg/THM | J42: Jul'25-Oct'25 | K42: 491 | L42: 450 | M42: 529 | N42: 546 | O42: 499 | P42: 477 | Q42: 493 | R42: 451 | S42: 499.16667 | T42: -0.19918699 | U42: Needs Attention
A43: 24 | B43: I | D43: Samanway Das | E43: Unit-III | F43: MBF Operation | G43: Reduce coal Injection Rate of Blast furnace 2 per day from ---- Kg/THM to ---- Kg/THM. | H43: Decresing | I43: Kg/THM | J43: Jul'25-Oct'25 | K43: 118 | L43: 100 | M43: 98.75 | N43: 82.58 | O43: 120.73 | P43: 119.86 | Q43: 118 | R43: 141 | S43: 113.48667 | T43: 0.25074074 | U43: Needs Attention
A44: 29 | B44: II | C44: 5152 | D44: Somnath Patra | E44: Unit-III | F44: Sinter Electrical | G44: Reduce the Specific Power Consumption of Sinter Plant 1 from 61kWh/MT to <45 kWh/MT per day. | H44: Decresing | I44: kWh/Ton | J44: Aug'25-Nov'25 | K44: 52.989 | L44: 45 | M44: 49.72 | N44: 61.39 | O44: 56.93 | P44: 49.46 | Q44: 53.22 | R44: 57.65 | S44: 54.728333 | T44: -0.21771603 | U44: Needs Attention
A45: 31 | B45: I | D45: Sugyan Dora | E45: Unit-IV | F45: DRI | G45: Productivity Improvement by enhancing Kilen#1 | H45: Increasing | I45: MT/Hr | J45: Sep'25-Dec'25 | K45: 3.83 | L45: 4 | M45: 3.96 | N45: 3.96 | O45: 3.74 | P45: 3.76 | Q45: 3.83 | R45: 3.8 | S45: 3.8416667 | T45: 0.068627451 | U45: Needs Attention
A46: 32 | B46: I | D46: Sugyan Dora | E46: Unit-IV | F46: DRI | G46: Productivity Improvement by enhancing Kilen#II | H46: Increasing | I46: MT/Hr | J46: Sep'25-Dec'25 | K46: 3.9 | L46: 4 | M46: 3.9 | N46: 3.97 | O46: 3.88 | P46: 3.84 | Q46: 3.88 | R46: 3.89 | S46: 3.8933333 | T46: -0.066666667 | U46: Needs Attention
A47: 33 | B47: I | D47: Sugyan Dora | E47: Unit-IV | F47: DRI | G47: Productivity Improvement by enhancing Kilen#III | H47: Increasing | I47: MT/Hr | J47: Sep'25-Dec'25 | K47: 3.76 | L47: 4 | M47: 3.38 | N47: 3.86 | O47: 3.68 | P47: 2.95 | Q47: 4.09 | R47: 3.97 | S47: 3.655 | T47: -0.4375 | U47: Needs Attention
A48: 34 | B48: I | D48: Sugyan Dora | E48: Unit-IV | F48: DRI | G48: Productivity Improvement by enhancing Kilen#IV | H48: Increasing | I48: MT/Hr | J48: Sep'25-Dec'25 | K48: 3.63 | L48: 4 | M48: 3.65 | N48: 3.53 | O48: 3.89 | P48: 2.8 | Q48: 4.04 | R48: 4.07 | S48: 3.6633333 | T48: 0.09009009 | U48: Needs Attention
A49: 35 | B49: II | C49: 48820 | D49: Kumar Dipendra | E49: Unit-IV | F49: CPP Operations | G49: Increasing Steam Generation in BF Gas Boiler(free fuel Based) from 21138 Ton/Month to > 24520 Ton/Month | H49: Increasing | I49: Ton/Month | J49: Mar-25-Oct-25 | K49: 22645 | L49: 24520 | M49: 22848 | N49: 11779 | O49: 20425 | P49: 21966 | Q49: 19276 | R49: 18872 | S49: 19194.333 | T49: -1.8403556 | U49: Needs Attention
A50: 37 | B50: II | C50: 0 | D50: Arijit Mondal | E50: Unit-IV | F50: CPP Operations | G50: Increase the Steam Generation rate of 85 TPH Boiler per month from 49 to 76 ton/hrs. | H50: Increasing | I50: Ton/hrs | J50: Jan-25-Nov-25 | K50: 31048 | L50: 54720 | M50: 26349 | N50: 38713 | O50: 51859 | P50: 37485 | Q50: 40115 | R50: 36362 | S50: 38480.5 | T50: 0.31397854 | U50: Needs Attention
A51: 38 | B51: I | C51: 45143 | D51: Arun Thatoi | E51: Unit-IV | F51: Central Electrical | G51: Increase Average Load Factor of Unit-IV from 72.49 % to >80 % per Day | H51: Increasing | I51: % | J51: Aug'25-Dec'25 | K51: 72.49 | L51: 80 | M51: 71.28 | N51: 74.85 | O51: 74.86 | P51: 78.85 | Q51: 73.82 | R51: 70.31 | S51: 73.995 | T51: 0.20039947 | U51: Needs Attention
A52: 54 | B52: I | C52: 4781 | D52: Anupam Basak | E52: Unit-III | F52: Quality | G52: To reduce the Avg Variation of Basicity of Sinter Plant 1 from 0.08 to 0.04 . | H52: Decresing | I52: 0 | J52: Aug'25-Oct'25 | K52: 0.1018 | L52: 0.04 | M52: 0.99 | N52: 0.106 | O52: 0.105 | P52: 0.106 | Q52: 0.102 | R52: 0.097 | S52: 0.251 | T52: -2.4142395 | U52: Needs Attention
A53: 55 | B53: I | C53: 80428 | D53: Atish Gupta | E53: Mackeil | F53: Sales & Marketing | G53: Improve on time Delivery of Finished Goods in Mackeil per month from 43 to 56%. | H53: Increasing | I53: % | J53: Apr'25-Sep'25 | K53: 43 | L53: 56 | M53: 41.722924 | N53: 49.878853 | O53: 36.903717 | S53: 42.835165 | T53: -0.012679644 | U53: Needs Attention
A54: 56 | B54: II | D54: Nagendra singh | E54: Unit-III | F54: MBF Operation | G54: Increase the Avg Productivity of MBF2 per day from 2.32 Ton/m3 to >3.606 Ton/m3 . | H54: Increasing | I54: Ton/m3 | J54: Jul'25-Dec'25 | K54: 2.32 | L54: 3.6 | M54: 2.71 | N54: 2.72 | O54: 2.48 | P54: 2.54 | Q54: 2.08 | R54: 2.07 | S54: 2.4333333 | T54: 0.088541667 | U54: Needs Attention
A55: 67 | B55: II | C55: 49844 | D55: Ashutosh Pathak | E55: Unit-IV | F55: BE -DRI Operation | G55: Reduced Diesal Consumption from 5.60 Ltr/Hrs to 5.0 Ltr/Hr | H55: Decresing | I55: Ltr/Hrs | J55: Jul'25-Dec'25 | K55: 4.13 | L55: 4 | M55: 5.36 | N55: 4.54 | O55: 4.83 | P55: 4.82 | Q55: 4.72 | S55: 4.854 | T55: -5.5692308 | U55: Needs Attention
A56: 14 | B56: II | C56: 5503 | D56: Alok Mandal | E56: Unit-III | F56: Operation | G56: Reduce the average Gox Venting Loss per month from 339 to 180 MT. | H56: Decresing | U56: No Data
A57: 15 | B57: II | C57: 48956 | D57: Sailesh Singh Yadav | E57: Unit-IV | F57: Operation | G57: Cr Recovery from 87 % to > 90% ( Grade - Cr-60 & C-0.50 %) in Ferro alloys division in AOD | H57: Increasing | I57: % | J57: Augt'25-Dec'25 | L57: 90 | U57: No Data
A58: 39 | B58: II | D58: Sashank Shekhar | E58: Unit-III | F58: MBF-Mechanical | G58: Increased Productivity of Pig Casting Machine -1 (Double Strand) | H58: Increasing | I58: MT/Day | J58: 2026-06-01 00:00:00 | K58: 572 | L58: 800 | U58: No Data
A59: 40 | B59: II | D59: Sashank Shekhar | E59: Unit-III | F59: MBF-Mechanical | G59: Increased Productivity of Pig Casting Machine -2 (Double Stand) | H59: Increasing | I59: MT/Day | J59: 2026-06-01 00:00:00 | K59: 520 | L59: 800 | U59: No Data
A60: 48 | B60: II | C60: 50360 | D60: Pratip Roy | E60: Unit-IV | F60: Business Excellence | G60: Reducing feeding variance from ------ to -------for yeild improvement . | H60: Decresing | I60: % | U60: No Data
A61: 52 | B61: II | C61: 2954 | D61: Amit Dahari | E61: Unit-III | F61: MBF Electrical | G61: Reduce the Avg Specific energy consumption of MBF per month from 134.4 kWH/THM to 125 KWH/THM. | H61: Decresing | I61: KWH/THM | K61: 134.4 | L61: 125 | U61: No Data
A62: 53 | B62: II | C62: 5733 | D62: Kalyan Lahiri | E62: Unit-III | F62: Supply Chain Management | G62: Increase the average service cost saving of jai Balaji Industries Ltd Unit-III per month from 17.8 Lakh to 19.58 Lakh. | H62: Increasing | I62: Lakh | K62: 17.8 | L62: 20 | U62: No Data
A63: 57 | B63: I | C63: 334 | D63: Bidyut Bikash Dinda | E63: Unit-III | F63: Coke Oven Mechanical | G63: Reduce the average monthly general Maintenance Cost per ton of Coke Oven Plant from ₹28.6 to <₹25. | H63: Decresing | I63: ₹/Ton | J63: Jul'25-Dec'25 | K63: 28.6 | L63: 25 | U63: No Data
A64: 58 | B64: II | C64: 7747 | D64: Prasanta Basu | E64: Unit-III | F64: ISO | G64: Reduction of Paper Consumption through Effective IMS Internal Audits & Competence-Based Training from 27620 to < 5524. | H64: Decresing | I64: Nos | J64: Jan'23-Jan'25 | K64: 27620 | L64: 5524 | U64: No Data
A65: 59 | B65: II | C65: 2712 | D65: Abdur Rowf | E65: Unit-III | F65: Store | G65: Reducing Non moving items of Central store values from 6.3Cr. to <3.15Cr. INR | H65: Decresing | I65: Cr | K65: 6.3 | L65: 3.15 | U65: No Data
A66: 60 | B66: I | C66: 30103 | D66: Suman Majumder | E66: JSBIL | F66: Operation (Chemist) | G66: Reducing the cost of laboratory operation by optimizing chemical and machine uses . | H66: Decresing | I66: 0 | U66: No Data
A67: 61 | B67: I | C67: 47015 | D67: Aniruddha Ray | E67: Unit-IV | F67: Accounts and Finance | G67: Reduce the Invoice processing time of unit IV from --- to -----. | H67: Decresing | I67: 0 | U67: No Data
A68: 62 | B68: I | C68: 4924 | D68: Ashok kumar Singh | E68: Unit-III | F68: Industrial Relationship | G68: Increase the Contractual Manpower engagement of Unit-III from ---- per month to 100 % . | H68: Increasing | I68: % | U68: No Data
A69: 64 | B69: II | C69: 7780 | D69: Hilary Joseph | E69: Unit-III | F69: Industrial Relationship | G69: Reducing Manpower cost /MT 4.58 cr from 3.67 cost/MT | H69: Decresing | I69: Cost/MT | U69: No Data
A70: 65 | B70: I | C70: 16027 | D70: Arijit Modi | E70: JSBIL | F70: Commercial | G70: To Reducing the Despatch cycle time from --- hrs to ---- hrs of Jai salasar. | H70: Decresing | U70: No Data
A71: 66 | B71: II | C71: 9517 | D71: PK Swain | E71: Unit-IV | F71: Electrical | G71: Improving power factor from ------- to -------- in Unit -IV. | H71: Increasing | U71: No Data
A72: 68 | B72: I | C72: 6388 | D72: Randhir Kumar | E72: Unit-III | F72: Business Excellence | U72: No Data
A73: 69 | B73: I | C73: 6389 | D73: Avinash Kumar Mahato | E73: Unit-III | F73: Business Excellence | U73: No Data
A74: 70 | B74: II | C74: 48624 | D74: Sidheswar Biswal | E74: Unit-IV | F74: Safety | G74: Reducing unsafe condition per months from 406 to < 203. | H74: Decresing | I74: Nos | U74: No Data
A75: 71 | B75: I | C75: 7799 | D75: Kamal kant | E75: Mackeil | F75: BE-Mackeil Opeeartion | U75: No Data
A76: 72 | B76: I | C76: 10223 | D76: Amitava Dasgupta | E76: HO | F76: DIP Marketing | G76: Re-establish the tender data base (tender missing) ------- reducing tender processing time from ----- to ----- without adverse implication. | I76: Nos | U76: No Data
A77: 73 | B77: II | C77: 10860 | D77: Souptik Mondal | E77: HO | F77: DIP Marketing | G77: Reducing the freight cost per Km /MT from 580 to <----. | I77: Per kM/MT | U77: No Data
A78: 74 | B78: II | C78: 11039 | D78: Soumen Pal | E78: HO | F78: DIP Marketing | G78: Re-establish the tendor data base (tendor missing) per month from -------to ----. | H78: Increasing | I78: Nos | U78: No Data
A79: 75 | B79: I | D79: Sanjib Pattnaik | E79: UNIT-I | F79: Human Resource | H79: Decresing | U79: No Data
A80: 76 | B80: I | C80: 10642 | D80: Amitava Mukherjee | E80: HO | F80: Human Resource | G80: Improve the Manpower engagement of HO from -- % per month to --- % per month. | H80: Increasing | I80: 0 | U80: No Data
A81: 77 | B81: I | C81: 10811 | D81: Roopam Rai | E81: HO | F81: Business Excellence | G81: Development of New Products with High Demand for Open Die Forgings Plant". | H81: Increasing | U81: No Data
A82: 78 | B82: II | C82: 3927 | D82: Subhash Ghosh | E82: Unit-III | F82: Civil | G82: Vendor cost optimization | H82: Decresing | U82: No Data
A83: 79 | B83: II | C83: 3069 | D83: Kamal Bandyopadhyay | E83: Unit-III | F83: Account | G83: Reduce Avg Planned vs. Actual Cost Variation of the MBF Plantper month from 1449 to 1232. | H83: Decresing | U83: No Data
A84: 80 | B84: II | D84: Prashnat Yadav | E84: Mackeil | F84: Estimation | G84: To Increased PO Conversation Ratio | H84: Increasing | U84: No Data
A85: 81 | B85: II | C85: 47561 | D85: Mohammad Ahmad | E85: Unit-IV | F85: Human Resource | G85: Optimize manpower cost of Unit -IV. | H85: Decresing | U85: No Data
